Workbook

Sheet BASE_COSTEO (2)
A1: Año | B1: Mes | C1: COMPLEJIDAD | D1: PROCEDIMIENTO | E1: CODIGO_CUPS | F1: TIEMPO_MINUTOS | G1: TIPO_REGISTRO | H1: CATEGORIA_COSTO | I1: ITEM | J1: CANTIDAD | K1: UNIDAD_MEDIDA | L1: COSTO_UNITARIO | M1: COSTO_TOTAL | N1: OBSERVACIONES
A2: 2026 | B2: Mayo | C2: Baja Complejidad | D2: Curación de BAJA COMPLEJIDAD | E2: 1965 | F2: 30 | G2: INSUMO | H2: INSUMO | I2: Guante examen talla M | J2: 4 | K2: UND | L2: 10948 | M2: 218.96 | N2: 2 PARES
A3: 2026 | B3: Mayo | C3: Baja Complejidad | D3: Curación de BAJA COMPLEJIDAD | E3: 1965 | F3: 30 | G3: INSUMO | H3: INSUMO | I3: Guante quirurgico esteril 7.0 | J3: 1 | K3: UND | L3: 1086.232 | M3: 1086.232 | N3: 1 PAR
A4: 2026 | B4: Mayo | C4: Baja Complejidad | D4: Curación de BAJA COMPLEJIDAD | E4: 1965 | F4: 30 | G4: INSUMO | H4: INSUMO | I4: Gasa esteril 7.5 X 7.5 sobre x 5 unid | J4: 4 | K4: UND | L4: 370 | M4: 1480
A5: 2026 | B5: Mayo | C5: Baja Complejidad | D5: Curación de BAJA COMPLEJIDAD | E5: 1965 | F5: 30 | G5: INSUMO | H5: INSUMO | I5: Solucion Salina 0.9% Bolsa 100 ml | J5: 1 | K5: UND | L5: 1965 | M5: 1965
A6: 2026 | B6: Mayo | C6: Baja Complejidad | D6: Curación de BAJA COMPLEJIDAD | E6: 1965 | F6: 30 | G6: INSUMO | H6: INSUMO | I6: Cinta adhesiva x 200cm Fixomull ( por centimetro) | J6: 1 | K6: UND | N6: 30 CM
A7: 2026 | B7: Mayo | C7: Baja Complejidad | D7: Curación de BAJA COMPLEJIDAD | E7: 1965 | F7: 30 | G7: INSUMO | H7: INSUMO | I7: Tapabocas Estandar 1405 | J7: 0.4 | K7: UND | L7: 135.66 | M7: 54.264
A8: 2026 | B8: Mayo | C8: Baja Complejidad | D8: Curación de BAJA COMPLEJIDAD | E8: 1965 | F8: 30 | G8: INSUMO | H8: INSUMO | I8: Bata Desechable con Manga No Esteril | J8: 2 | K8: UND | L8: 3808 | M8: 7616
A9: 2026 | B9: Mayo | C9: Baja Complejidad | D9: Curación de BAJA COMPLEJIDAD | E9: 1965 | F9: 30 | G9: INSUMO | H9: INSUMO | I9: Gorro Desechable Estandar Blanco | J9: 0.4 | K9: UND | L9: 111.86 | M9: 44.744
A10: 2026 | B10: Mayo | C10: Baja Complejidad | D10: Curación de BAJA COMPLEJIDAD | E10: 1965 | F10: 30 | G10: INSUMO | H10: INSUMO | I10: acido hipocloroso | J10: 2 | K10: UND
A11: 2026 | B11: Mayo | C11: Baja Complejidad | D11: Curación de BAJA COMPLEJIDAD | E11: 1965 | F11: 30 | G11: INSUMO | H11: INSUMO | I11: Toalla de Manos Pre-cortada Natural R7 | J11: 2 | K11: UND | L11: 17888.08 | M11: 357.7616
A12: 2026 | B12: Mayo | C12: Baja Complejidad | D12: Curación de BAJA COMPLEJIDAD | E12: 1965 | F12: 30 | G12: INSUMO | H12: INSUMO | I12: Hoja para bisturi 15 | J12: 1 | K12: UND | L12: 337.38379 | M12: 337.38379
A13: 2026 | B13: Mayo | C13: Baja Complejidad | D13: Curación de BAJA COMPLEJIDAD | E13: 1965 | F13: 30 | G13: INSUMO | H13: INSUMO | I13: Venda de algodon 6 x 5 | J13: 1 | K13: UND | L13: 1843.3333 | M13: 1843.3333
A14: 2026 | B14: Mayo | C14: Baja Complejidad | D14: Curación de BAJA COMPLEJIDAD | E14: 1965 | F14: 30 | G14: INSUMO | H14: INSUMO | I14: Venda elastica 6 x 5 | J14: 1 | K14: UND | L14: 2346 | M14: 2346
A15: 2026 | B15: Mayo | C15: Baja Complejidad | D15: Curación de BAJA COMPLEJIDAD | E15: 1965 | F15: 30 | G15: MANO_OBRA | H15: MANO_OBRA | I15: Enfermera | J15: 30 | K15: MINUTOS
A16: 2026 | B16: Mayo | C16: Baja Complejidad | D16: Curación de BAJA COMPLEJIDAD | E16: 1965 | F16: 30 | G16: MANO_OBRA | H16: MANO_OBRA | I16: Auxiliar enfermeria | J16: 30 | K16: MINUTOS
A17: 2026 | B17: Mayo | C17: Baja Complejidad | D17: Curación de BAJA COMPLEJIDAD | E17: 1965 | F17: 30 | G17: GASTO_ADMINISTRATIVO | H17: GASTO_ADMINISTRATIVO | I17: Gasto administrativo | J17: 30 | K17: MINUTOS | M17: 12657
A18: 2026 | B18: Mayo | C18: Baja Complejidad | D18: Curación de BAJA COMPLEJIDAD | E18: 360001 | G18: INSUMO | H18: INSUMO | I18: Granulox Hemoglobina Spray | K18: Unidad | M18: 893800
A19: 2026 | B19: Mayo | C19: Baja Complejidad | D19: Curación de BAJA COMPLEJIDAD | E19: 360102 | G19: INSUMO | H19: INSUMO | I19: Granudacyn Solución 1000 ml | K19: Unidad | M19: 251100
A20: 2026 | B20: Mayo | C20: Baja Complejidad | D20: Curación de BAJA COMPLEJIDAD | E20: 360104 | G20: INSUMO | H20: INSUMO | I20: Granudacyn Solución 1000 ml NPWT | K20: Unidad | M20: 261100
A21: 2026 | B21: Mayo | C21: Baja Complejidad | D21: Curación de BAJA COMPLEJIDAD | E21: 360100 | G21: INSUMO | H21: INSUMO | I21: Granudacyn Solución 250 ml Spray | K21: Unidad | M21: 80300
A22: 2026 | B22: Mayo | C22: Baja Complejidad | D22: Curación de BAJA COMPLEJIDAD | E22: 360150 | G22: INSUMO | H22: INSUMO | I22: Granudacyn Solución 50 ml Spray | K22: Unidad | M22: 76800
A23: 2026 | B23: Mayo | C23: Baja Complejidad | D23: Curación de BAJA COMPLEJIDAD | E23: 360101 | G23: INSUMO | H23: INSUMO | I23: Granudacyn Solución 500 ml | K23: Unidad | M23: 140600
A24: 2026 | B24: Mayo | C24: Baja Complejidad | D24: Curación de BAJA COMPLEJIDAD | E24: 360103 | G24: INSUMO | H24: INSUMO | I24: Granudacyn Solución 500 ml NPWT | K24: Unidad | M24: 150600
A25: 2026 | B25: Mayo | C25: Baja Complejidad | D25: Curación de BAJA COMPLEJIDAD | E25: 709900 | G25: INSUMO | H25: INSUMO | I25: Exufiber 5 x 5 cm | K25: Caja X 10 | M25: 13500
A26: 2026 | B26: Mayo | C26: Baja Complejidad | D26: Curación de BAJA COMPLEJIDAD | E26: 709902 | G26: INSUMO | H26: INSUMO | I26: Exufiber 10 x 12 cm | K26: Caja X 10 | M26: 28800
A27: 2026 | B27: Mayo | C27: Baja Complejidad | D27: Curación de BAJA COMPLEJIDAD | E27: 709903 | G27: INSUMO | H27: INSUMO | I27: Exufiber 15 x 15 cm | K27: Caja X 10 | M27: 63400
A28: 2026 | B28: Mayo | C28: Baja Complejidad | D28: Curación de BAJA COMPLEJIDAD | E28: 709909 | G28: INSUMO | H28: INSUMO | I28: Exufiber 2 x 45 cm | K28: Caja X 5 | M28: 38400
A29: 2026 | B29: Mayo | C29: Baja Complejidad | D29: Curación de BAJA COMPLEJIDAD | E29: 709904 | G29: INSUMO | H29: INSUMO | I29: Exufiber 20 x 30 cm | K29: Caja X 5 | M29: 169000
... A112: 2026 | B112: Mayo | C112: Baja Complejidad | D112: Curación de BAJA COMPLEJIDAD | E112: 2444 | G112: INSUMO | H112: INSUMO | I112: Tubifast 10m Violeta | K112: Unidad | M112: 200900
A113: 2026 | B113: Mayo | C113: Mediana Complejidad | D113: Curación de MEDIANA COMPLEJIDAD | E113: 26180 | F113: 45 | G113: INSUMO | H113: INSUMO | I113: Guante examen talla M | J113: 4 | K113: UND | L113: 10948 | M113: 43792
A114: 2026 | B114: Mayo | C114: Mediana Complejidad | D114: Curación de MEDIANA COMPLEJIDAD | E114: 26180 | F114: 45 | G114: INSUMO | H114: INSUMO | I114: Guante quirurgico esteril 7.0 | J114: 2 | K114: UND | L114: 1086.232 | M114: 2172.464
A115: 2026 | B115: Mayo | C115: Mediana Complejidad | D115: Curación de MEDIANA COMPLEJIDAD | E115: 26180 | F115: 45 | G115: INSUMO | H115: INSUMO | I115: Gasa esteril 7.5 X 7.5 sobre x 5 unid | J115: 6 | K115: UND | L115: 370 | M115: 2220
A116: 2026 | B116: Mayo | C116: Mediana Complejidad | D116: Curación de MEDIANA COMPLEJIDAD | E116: 26180 | F116: 45 | G116: INSUMO | H116: INSUMO | I116: Solucion Salina 0.9% Bolsa 100 ml | J116: 2 | K116: UND | L116: 1965 | M116: 3930
A117: 2026 | B117: Mayo | C117: Mediana Complejidad | D117: Curación de MEDIANA COMPLEJIDAD | E117: 26180 | F117: 45 | G117: INSUMO | H117: INSUMO | I117: Cinta adhesiva x 200cm Fixomull | J117: 1 | K117: UND | L117: 26180 | M117: 26180
A118: 2026 | B118: Mayo | C118: Mediana Complejidad | D118: Curación de MEDIANA COMPLEJIDAD | E118: 26180 | F118: 45 | G118: INSUMO | H118: INSUMO | I118: Tapabocas Estandar 1405 | J118: 0.4 | K118: UND | L118: 135.66 | M118: 54.264
A119: 2026 | B119: Mayo | C119: Mediana Complejidad | D119: Curación de MEDIANA COMPLEJIDAD | E119: 26180 | F119: 45 | G119: INSUMO | H119: INSUMO | I119: Bata Desechable con Manga No Esteril | J119: 2 | K119: UND | L119: 3808 | M119: 7616
A120: 2026 | B120: Mayo | C120: Mediana Complejidad | D120: Curación de MEDIANA COMPLEJIDAD | E120: 26180 | F120: 45 | G120: INSUMO | H120: INSUMO | I120: Gorro Desechable Estandar Blanco | J120: 0.4 | K120: UND | L120: 111.86 | M120: 44.744
A121: 2026 | B121: Mayo | C121: Mediana Complejidad | D121: Curación de MEDIANA COMPLEJIDAD | E121: 26180 | F121: 45 | G121: INSUMO | H121: INSUMO | I121: acido hipocloroso | J121: 2 | K121: UND
A122: 2026 | B122: Mayo | C122: Mediana Complejidad | D122: Curación de MEDIANA COMPLEJIDAD | E122: 26180 | F122: 45 | G122: INSUMO | H122: INSUMO | I122: Toalla de Manos Pre-cortada Natural R7 | J122: 2 | K122: UND | L122: 17888.08 | M122: 357.7616
A123: 2026 | B123: Mayo | C123: Mediana Complejidad | D123: Curación de MEDIANA COMPLEJIDAD | E123: 26180 | F123: 45 | G123: INSUMO | H123: INSUMO | I123: Hoja para bisturi 15 | J123: 1 | K123: UND | L123: 337.38379 | M123: 337.38379
A124: 2026 | B124: Mayo | C124: Mediana Complejidad | D124: Curación de MEDIANA COMPLEJIDAD | E124: 26180 | F124: 45 | G124: INSUMO | H124: INSUMO | I124: Venda de algodon 6 x 5 | J124: 1 | K124: UND | L124: 1843.3333 | M124: 1843.3333
A125: 2026 | B125: Mayo | C125: Mediana Complejidad | D125: Curación de MEDIANA COMPLEJIDAD | E125: 26180 | F125: 45 | G125: INSUMO | H125: INSUMO | I125: Venda elastica 6 x 5 | J125: 1 | K125: UND | L125: 2346 | M125: 2346
A126: 2026 | B126: Mayo | C126: Mediana Complejidad | D126: Curación de MEDIANA COMPLEJIDAD | E126: 26180 | F126: 45 | G126: MANO_OBRA | H126: MANO_OBRA | I126: Enfermera | J126: 45 | K126: MINUTO
A127: 2026 | B127: Mayo | C127: Mediana Complejidad | D127: Curación de MEDIANA COMPLEJIDAD | E127: 26180 | F127: 45 | G127: MANO_OBRA | H127: MANO_OBRA | I127: Auxiliar enfermeria | J127: 45 | K127: MINUTO
A128: 2026 | B128: Mayo | C128: Mediana Complejidad | D128: Curación de MEDIANA COMPLEJIDAD | E128: 26180 | F128: 45 | G128: GASTO_ADMINISTRATIVO | H128: GASTO_ADMINISTRATIVO | I128: Gasto administrativo | J128: 45 | K128: MINUTOS | M128: 22693
A129: 2026 | B129: Mayo | C129: Mediana Complejidad | D129: Curación de MEDIANA COMPLEJIDAD | E129: 360001 | G129: INSUMO | H129: INSUMO | I129: Granulox Hemoglobina Spray | K129: Unidad | M129: 893800
A130: 2026 | B130: Mayo | C130: Mediana Complejidad | D130: Curación de MEDIANA COMPLEJIDAD | E130: 360102 | G130: INSUMO | H130: INSUMO | I130: Granudacyn Solución 1000 ml | K130: Unidad | M130: 251100
A131: 2026 | B131: Mayo | C131: Mediana Complejidad | D131: Curación de MEDIANA COMPLEJIDAD | E131: 360104 | G131: INSUMO | H131: INSUMO | I131: Granudacyn Solución 1000 ml NPWT | K131: Unidad | M131: 261100
A132: 2026 | B132: Mayo | C132: Mediana Complejidad | D132: Curación de MEDIANA COMPLEJIDAD | E132: 360100 | G132: INSUMO | H132: INSUMO | I132: Granudacyn Solución 250 ml Spray | K132: Unidad | M132: 80300
A133: 2026 | B133: Mayo | C133: Mediana Complejidad | D133: Curación de MEDIANA COMPLEJIDAD | E133: 360150 | G133: INSUMO | H133: INSUMO | I133: Granudacyn Solución 50 ml Spray | K133: Unidad | M133: 76800
A134: 2026 | B134: Mayo | C134: Mediana Complejidad | D134: Curación de MEDIANA COMPLEJIDAD | E134: 360101 | G134: INSUMO | H134: INSUMO | I134: Granudacyn Solución 500 ml | K134: Unidad | M134: 140600
A135: 2026 | B135: Mayo | C135: Mediana Complejidad | D135: Curación de MEDIANA COMPLEJIDAD | E135: 360103 | G135: INSUMO | H135: INSUMO | I135: Granudacyn Solución 500 ml NPWT | K135: Unidad | M135: 150600
A136: 2026 | B136: Mayo | C136: Mediana Complejidad | D136: Curación de MEDIANA COMPLEJIDAD | E136: 709900 | G136: INSUMO | H136: INSUMO | I136: Exufiber 5 x 5 cm | K136: Caja X 10 | M136: 13500
A137: 2026 | B137: Mayo | C137: Mediana Complejidad | D137: Curación de MEDIANA COMPLEJIDAD | E137: 709902 | G137: INSUMO | H137: INSUMO | I137: Exufiber 10 x 12 cm | K137: Caja X 10 | M137: 28800
A138: 2026 | B138: Mayo | C138: Mediana Complejidad | D138: Curación de MEDIANA COMPLEJIDAD | E138: 709903 | G138: INSUMO | H138: INSUMO | I138: Exufiber 15 x 15 cm | K138: Caja X 10 | M138: 63400
A139: 2026 | B139: Mayo | C139: Mediana Complejidad | D139: Curación de MEDIANA COMPLEJIDAD | E139: 709909 | G139: INSUMO | H139: INSUMO | I139: Exufiber 2 x 45 cm | K139: Caja X 5 | M139: 38400
A140: 2026 | B140: Mayo | C140: Mediana Complejidad | D140: Curación de MEDIANA COMPLEJIDAD | E140: 709904 | G140: INSUMO | H140: INSUMO | I140: Exufiber 20 x 30 cm | K140: Caja X 5 | M140: 169000
... A223: 2026 | B223: Mayo | C223: Mediana Complejidad | D223: Curación de MEDIANA COMPLEJIDAD | E223: 2444 | G223: INSUMO | H223: INSUMO | I223: Tubifast 10m Violeta | K223: Unidad | M223: 200900
A224: 2026 | B224: Mayo | C224: Alta Complejidad | D224: Curación de ALTA COMPLEJIDAD | E224: 26180 | F224: 120 | G224: INSUMO | H224: INSUMO | I224: Guante examen talla M | J224: 4 | K224: UND | L224: 10948 | M224: 43792
A225: 2026 | B225: Mayo | C225: Alta Complejidad | D225: Curación de ALTA COMPLEJIDAD | E225: 26180 | F225: 120 | G225: INSUMO | H225: INSUMO | I225: Guante quirurgico esteril 7.0 | J225: 2 | K225: UND | L225: 1086.232 | M225: 2172.464
A226: 2026 | B226: Mayo | C226: Alta Complejidad | D226: Curación de ALTA COMPLEJIDAD | E226: 26180 | F226: 120 | G226: INSUMO | H226: INSUMO | I226: Gasa esteril 7.5 X 7.5 sobre x 5 unid | J226: 10 | K226: UND | L226: 370 | M226: 3700
A227: 2026 | B227: Mayo | C227: Alta Complejidad | D227: Curación de ALTA COMPLEJIDAD | E227: 26180 | F227: 120 | G227: INSUMO | H227: INSUMO | I227: Solucion Salina 0.9% Bolsa 500 ml | J227: 2 | K227: UND | L227: 2643 | M227: 5286
A228: 2026 | B228: Mayo | C228: Alta Complejidad | D228: Curación de ALTA COMPLEJIDAD | E228: 26180 | F228: 120 | G228: INSUMO | H228: INSUMO | I228: Cinta adhesiva x 200cm Fixomull | J228: 1 | K228: UND | L228: 26180 | M228: 26180
A229: 2026 | B229: Mayo | C229: Alta Complejidad | D229: Curación de ALTA COMPLEJIDAD | E229: 26180 | F229: 120 | G229: INSUMO | H229: INSUMO | I229: Tapabocas Estandar 1405 | J229: 0.4 | K229: UND | L229: 135.66 | M229: 54.264
A230: 2026 | B230: Mayo | C230: Alta Complejidad | D230: Curación de ALTA COMPLEJIDAD | E230: 26180 | F230: 120 | G230: INSUMO | H230: INSUMO | I230: Bata Desechable con Manga No Esteril | J230: 2 | K230: UND | L230: 3808 | M230: 7616
A231: 2026 | B231: Mayo | C231: Alta Complejidad | D231: Curación de ALTA COMPLEJIDAD | E231: 26180 | F231: 120 | G231: INSUMO | H231: INSUMO | I231: Gorro Desechable Estandar Blanco | J231: 0.4 | K231: UND | L231: 111.86 | M231: 44.744
A232: 2026 | B232: Mayo | C232: Alta Complejidad | D232: Curación de ALTA COMPLEJIDAD | E232: 26180 | F232: 120 | G232: INSUMO | H232: INSUMO | I232: Solucion desinfectante ( evolución de la herida) | J232: 2
A233: 2026 | B233: Mayo | C233: Alta Complejidad | D233: Curación de ALTA COMPLEJIDAD | E233: 26180 | F233: 120 | G233: INSUMO | H233: INSUMO | I233: Toalla de Manos Pre-cortada Natural R7 | J233: 2 | L233: 17888.08 | M233: 357.7616
A234: 2026 | B234: Mayo | C234: Alta Complejidad | D234: Curación de ALTA COMPLEJIDAD | E234: 26180 | F234: 120 | G234: INSUMO | H234: INSUMO | I234: Hoja para bisturi 15 | J234: 2 | K234: UND | L234: 337.38379 | M234: 674.76758
A235: 2026 | B235: Mayo | C235: Alta Complejidad | D235: Curación de ALTA COMPLEJIDAD | E235: 26180 | F235: 120 | G235: INSUMO | H235: INSUMO | I235: Venda de algodon 6 x 5 | J235: 2 | K235: UND | L235: 1843.3333 | M235: 3686.6667
A236: 2026 | B236: Mayo | C236: Alta Complejidad | D236: Curación de ALTA COMPLEJIDAD | E236: 26180 | F236: 120 | G236: INSUMO | H236: INSUMO | I236: Venda elastica 6 x 5 | J236: 2 | K236: UND | L236: 2346 | M236: 4692
A237: 2026 | B237: Mayo | C237: Alta Complejidad | D237: Curación de ALTA COMPLEJIDAD | E237: 26180 | F237: 120 | G237: MANO_OBRA | H237: MANO_OBRA | I237: Enfermera | J237: 120 | K237: MINUTO
A238: 2026 | B238: Mayo | C238: Alta Complejidad | D238: Curación de ALTA COMPLEJIDAD | E238: 26180 | F238: 120 | G238: MANO_OBRA | H238: MANO_OBRA | I238: Auxiliar enfermeria | J238: 120 | K238: MINUTO
A239: 2026 | B239: Mayo | C239: Alta Complejidad | D239: Curación de ALTA COMPLEJIDAD | E239: 26180 | F239: 120 | G239: GASTO_ADMINISTRATIVO | H239: GASTO_ADMINISTRATIVO | I239: Gasto administrativo | J239: 120 | K239: MINUTOS | M239: 34619.803
A240: 2026 | B240: Mayo | C240: Alta Complejidad | D240: Curación de ALTA COMPLEJIDAD | E240: 360001 | G240: INSUMO | H240: INSUMO | I240: Granulox Hemoglobina Spray | K240: Unidad | M240: 893800
A241: 2026 | B241: Mayo | C241: Alta Complejidad | D241: Curación de ALTA COMPLEJIDAD | E241: 360102 | G241: INSUMO | H241: INSUMO | I241: Granudacyn Solución 1000 ml | K241: Unidad | M241: 251100
A242: 2026 | B242: Mayo | C242: Alta Complejidad | D242: Curación de ALTA COMPLEJIDAD | E242: 360104 | G242: INSUMO | H242: INSUMO | I242: Granudacyn Solución 1000 ml NPWT | K242: Unidad | M242: 261100
A243: 2026 | B243: Mayo | C243: Alta Complejidad | D243: Curación de ALTA COMPLEJIDAD | E243: 360100 | G243: INSUMO | H243: INSUMO | I243: Granudacyn Solución 250 ml Spray | K243: Unidad | M243: 80300
A244: 2026 | B244: Mayo | C244: Alta Complejidad | D244: Curación de ALTA COMPLEJIDAD | E244: 360150 | G244: INSUMO | H244: INSUMO | I244: Granudacyn Solución 50 ml Spray | K244: Unidad | M244: 76800
A245: 2026 | B245: Mayo | C245: Alta Complejidad | D245: Curación de ALTA COMPLEJIDAD | E245: 360101 | G245: INSUMO | H245: INSUMO | I245: Granudacyn Solución 500 ml | K245: Unidad | M245: 140600
A246: 2026 | B246: Mayo | C246: Alta Complejidad | D246: Curación de ALTA COMPLEJIDAD | E246: 360103 | G246: INSUMO | H246: INSUMO | I246: Granudacyn Solución 500 ml NPWT | K246: Unidad | M246: 150600
A247: 2026 | B247: Mayo | C247: Alta Complejidad | D247: Curación de ALTA COMPLEJIDAD | E247: 709900 | G247: INSUMO | H247: INSUMO | I247: Exufiber 5 x 5 cm | K247: Caja X 10 | M247: 13500
A248: 2026 | B248: Mayo | C248: Alta Complejidad | D248: Curación de ALTA COMPLEJIDAD | E248: 709902 | G248: INSUMO | H248: INSUMO | I248: Exufiber 10 x 12 cm | K248: Caja X 10 | M248: 28800
A249: 2026 | B249: Mayo | C249: Alta Complejidad | D249: Curación de ALTA COMPLEJIDAD | E249: 709903 | G249: INSUMO | H249: INSUMO | I249: Exufiber 15 x 15 cm | K249: Caja X 10 | M249: 63400
A250: 2026 | B250: Mayo | C250: Alta Complejidad | D250: Curación de ALTA COMPLEJIDAD | E250: 709909 | G250: INSUMO | H250: INSUMO | I250: Exufiber 2 x 45 cm | K250: Caja X 5 | M250: 38400
A251: 2026 | B251: Mayo | C251: Alta Complejidad | D251: Curación de ALTA COMPLEJIDAD | E251: 709904 | G251: INSUMO | H251: INSUMO | I251: Exufiber 20 x 30 cm | K251: Caja X 5 | M251: 169000
... A334: 2026 | B334: Mayo | C334: Alta Complejidad | D334: Curación de ALTA COMPLEJIDAD | E334: 2444 | G334: INSUMO | H334: INSUMO | I334: Tubifast 10m Violeta | K334: Unidad | M334: 200900
A335: 2026 | B335: Mayo | C335: Manejo de Ostomias | D335: Curación Manejo de Ostomias | E335: 10948 | F335: 90 | G335: INSUMO | H335: INSUMO | I335: Solucion Salina 0.9% Bolsa 100 ml | J335: 1 | K335: UND | L335: 1965 | M335: 1965 | N335: 6 PARES
A336: 2026 | B336: Mayo | C336: Manejo de Ostomias | D336: Curación Manejo de Ostomias | E336: 10948 | F336: 90 | G336: INSUMO | H336: INSUMO | I336: agua esteril 100 ml | J336: 1
A337: 2026 | B337: Mayo | C337: Manejo de Ostomias | D337: Curación Manejo de Ostomias | E337: 10948 | F337: 90 | G337: INSUMO | H337: INSUMO | I337: Bata Desechable con Manga No Esteril (según condición) | J337: 2 | K337: UND
A338: 2026 | B338: Mayo | C338: Manejo de Ostomias | D338: Curación Manejo de Ostomias | E338: 10948 | F338: 90 | G338: INSUMO | H338: INSUMO | I338: Gorro Desechable Estandar Blanco | J338: 0.4 | K338: UND | L338: 111.86 | M338: 44.744
A339: 2026 | B339: Mayo | C339: Manejo de Ostomias | D339: Curación Manejo de Ostomias | E339: 10948 | F339: 90 | G339: INSUMO | H339: INSUMO | I339: Toalla de Manos Pre-cortada Natural R7 | J339: 0.5 | K339: UND | L339: 17888.08 | M339: 89.4404
A340: 2026 | B340: Mayo | C340: Manejo de Ostomias | D340: Curación Manejo de Ostomias | E340: 10948 | F340: 90 | G340: INSUMO | H340: INSUMO | I340: Guante examen talla M | J340: 1 | K340: UND | L340: 10948 | M340: 10948
A341: 2026 | B341: Mayo | C341: Manejo de Ostomias | D341: Curación Manejo de Ostomias | E341: 10948 | F341: 90 | G341: INSUMO | H341: INSUMO | I341: pasta | J341: 1
A342: 2026 | B342: Mayo | C342: Manejo de Ostomias | D342: Curación Manejo de Ostomias | E342: 10948 | F342: 90 | G342: INSUMO | H342: INSUMO | I342: polvos adapt | J342: 1
A343: 2026 | B343: Mayo | C343: Manejo de Ostomias | D343: Curación Manejo de Ostomias | E343: 10948 | F343: 90 | G343: INSUMO | H343: INSUMO | I343: Barrera plana o convexa (depende del tipo de estoma) | J343: 1
A344: 2026 | B344: Mayo | C344: Manejo de Ostomias | D344: Curación Manejo de Ostomias | E344: 10948 | F344: 90 | G344: INSUMO | H344: INSUMO | I344: Bolsa colostomia | J344: 1
A345: 2026 | B345: Mayo | C345: Manejo de Ostomias | D345: Curación Manejo de Ostomias | E345: 10948 | F345: 90 | G345: INSUMO | H345: INSUMO | I345: protector cutaneo | J345: 1
A346: 2026 | B346: Mayo | C346: Manejo de Ostomias | D346: Curación Manejo de Ostomias | E346: 10948 | F346: 90 | G346: INSUMO | H346: INSUMO | I346: removedor de adhesivo | J346: 1
...

Sheet DashBoard
C9: 💰 COSTO TOTAL A 6 MESES | E9: 💊 COSTO TOTAL INSUMOS POR MES | G9: 📊 COSTO PROMEDIO X COMPLEJIDAD | I9: 👷 COSTO CURACIÓN DIARIA | K9: 🏢 GASTOS ADMINISTRATIVOS POR MES | M9: ⏰ TIEMPO PROMEDIO
C10: =SUM(BASE_COSTEO!M2:M680) -> 1.1102312e+08 | E10: =SUMIF(BASE_COSTEO!$G$2:$G$680,"INSUMO",BASE_COSTEO!$M$2:$M$680)/6 -> 364946.57 | G10: =AVERAGE(BASE_COSTEO!M2:M680) -> 163509.76 | I10: =AVERAGEIF(BASE_COSTEO!$H$2:$H$680,"MANO_OBRA",BASE_COSTEO!$M$2:$M$680)/6 -> 178866.26 | K10: =SUMIF(BASE_COSTEO!$G$2:$G$680,"GASTO_ADMINISTRATIVO",BASE_COSTEO!$M$2:$M$680)/6 -> 2616433.2 | M10: =ROUND(AVERAGEIF(BASE_COSTEO!$K$2:$K$680,"MINUTOS",BASE_COSTEO!$J$2:$J$680),2) & " min" -> 48 min
F17: Etiquetas de fila | G17: Suma de COSTO_TOTAL | K17: Etiquetas de fila | L17: COSTO_TOTAL_
F18: Baja Complejidad | G18: 11294501 | K18: MANO_OBRA | L18: 67611446
F19: GASTO_ADMINISTRATIVO | G19: 15610000 | K19: INSUMO ALTA TECNOLOGIA | L19: 25523400
F20: Mediana Complejidad | G20: 29680186 | K20: GASTO_ADMINISTRATIVO | L20: 15698599
F21: Alta Complejidad | G21: 54438438 | K21: INSUMO | L21: 2189679.4
F22: Total general | G22: 1.1102312e+08 | K22: Total general | L22: 1.1102312e+08
C27: 💰 INGRESOS TOTALES A 6 MESES | E27: 💊 UTILIDAD TOTAL | G27: 📊 % MARGEN UTILIDAD | I27: 👷 PROCEDIMIENTO MAS RENTABLE | K27: 🏢 PROYECCIÓN MENSUAL | M27: ⏰ PUNTO EQUILIBRIO OPERACIONAL
C28: =SUM(BASE_COSTEO!$R$2:$R$680)+SUM(BASE_COSTEO!$V$2:$V$680)+SUM(BASE_COSTEO!$Z$2:$Z$680) -> 1.161278e+08 | E28: =(SUM(BASE_COSTEO!$R$2:$R$680)+SUM(BASE_COSTEO!$V$2:$V$680)+SUM(BASE_COSTEO!$Z$2:$Z$680))-SUM(BASE_COSTEO!$M$2:$M$680) -> 5104680 | G28: =(C28-C10)/C10 -> 0.045978529 | I28: {=_xlfn.LET( _xlpm.procedimientos,_xlfn.UNIQUE(_xlfn._xlws.FILTER(BASE_COSTEO!$C$2:$C$680,BASE_COSTEO!$C$2:$C$680<>"")), _xlpm.utilidades,_xlfn.MAP(_xlpm.procedimientos,_xlfn.LAMBDA(_xlpm.p, SUMIFS(BASE_COSTEO!$R$2:$R$680,BASE_COSTEO!$C$2:$C$680,_xlpm.p)+ SUMIFS(BASE_COSTEO!$V$2:$V$680,BASE_COSTEO!$C$2:$C$680,_xlpm.p)+ SUMIFS(BASE_COSTEO!$Z$2:$Z$680,BASE_COSTEO!$C$2:$C$680,_xlpm.p)- SUMIFS(BASE_COSTEO!$M$2:$M$680,BASE_COSTEO!$C$2:$C$680,_xlpm.p) )), INDEX(_xlpm.procedimientos,MATCH(MAX(_xlpm.utilidades),_xlpm.utilidades,0)) )} -> Alta Complejidad | K28: =((SUM(BASE_COSTEO!$R$2:$R$680)+SUM(BASE_COSTEO!$V$2:$V$680)+SUM(BASE_COSTEO!$Z$2:$Z$680)))/6 -> 19354634 | M28: {=IFERROR(ROUNDUP(SUM(BASE_COSTEO!$M$2:$M$680)/(((SUM(BASE_COSTEO!$R$2:$R$680)+SUM(BASE_COSTEO!$V$2:$V$680)+SUM(BASE_COSTEO!$Z$2:$Z$680))-SUM(BASE_COSTEO!$M$2:$M$680))/COUNTA(_xlfn.UNIQUE(_xlfn._xlws.FILTER(BASE_COSTEO!$D$2:$D$680,BASE_COSTEO!$D$2:$D$680<>"")))),0),0)&" Curaciones"} -> 87 Curaciones
D34: Etiquetas de fila | E34: % UTILIDAD ALTA COMPLEJIDAD_ | F34: % UTILIDAD MEDIANA COMPLEJIDAD_ | G34: % UTILIDAD BAJA COMPLEJIDAD_
D35: Mayo | E35: 5.5 | F35: 2.5 | G35: 2.5
D36: Junio | E36: 5.5 | F36: 2.5 | G36: 2.5
D37: Julio | E37: 5.5 | F37: 2.5 | G37: 2.5
D38: Agosto | E38: 5.5 | F38: 2.5 | G38: 2.5
D39: Septiembre | E39: 5.5 | F39: 2.5 | G39: 2.5
D40: Octubre | E40: 5.5 | F40: 2.5 | G40: 2.5
D41: Noviembre | E41: 5.5 | F41: 2.5 | G41: 2.5
D42: Total general | E42: 38.5 | F42: 17.5 | G42: 17.5
E48: CATEGORIA_COSTO | F48: INSUMO ALTA TECNOLOGIA
E49: PROCEDIMIENTO | F49: Curación de BAJA COMPLEJIDAD
E50: Mes | F50: Mayo
E52: Nombre | F52: _ | G52: Costo
E53: Mepilex Transfer Ag 15 x 20 cm | G53: 224100
E54: Mepilex Border Ag 10 x 30 cm | G54: 204000
E55: Mepilex Border Ag 10 x 25 cm | G55: 174700
E56: Mepilex Border Ag 10 x 20 cm | G56: 141600
E57: Mepilex Ag 15 x 15 cm | G57: 114900
E58: Mepilex Border Ag 10 x 10 cm | G58: 49200
E59: Mepilex Transfer 15 x 20 cm | G59: 49000
E60: Mextra Superabsorbent 17.5x22.5 cm | G60: 39800
E61: Mextra Superabsorbent 12.5x22.5 cm | G61: 38000
E62: Exufiber Ag+ 10 x 12 cm | G62: 36700
E63: Mepilex 15 x 15 cm | G63: 36700
E64: Exufiber 10 x 12 cm | G64: 28800
... E68: Total general | G68: 1215400

Sheet BASE_COSTEO
A1: Año | B1: Mes | C1: COMPLEJIDAD | D1: PROCEDIMIENTO | E1: CODIGO_CUPS | F1: TIEMPO_MINUTOS | G1: TIPO_REGISTRO | H1: CATEGORIA_COSTO | I1: ITEM | J1: CANTIDAD CURACIONES | K1: UNIDAD_MEDIDA | L1: COSTO_UNITARIO | M1: COSTO_TOTAL | N1: OBSERVACIONES | O1: PRECIO VENTA | P1: COSTO ALTA COMPLEJIDAD | Q1: % INCRE_ALTA | R1: PRECIO VTA ALTA COMPLEJIDAD | S1: % UTILIDAD ALTA COMPLEJIDAD | T1: COSTO MEDIANA COMPLEJIDAD | U1: % INCRE MEDIA | V1: PRECIO VTA MEDIANA COMPLEJIDAD | W1: % UTILIDAD MEDIANA COMPLEJIDAD | X1: COSTO BAJA COMPLEJIDAD | Y1: % INCRE BAJA | Z1: PRECIO VTA BAJA COMPLEJIDAD | AA1: % UTILIDAD BAJA COMPLEJIDAD | AB1: % CRECIMIENTO
A2: 2026 | B2: Mayo | C2: Gasto Administrativo | D2: Gasto Administrativo | G2: GASTO_ADMINISTRATIVO | H2: GASTO_ADMINISTRATIVO | I2: Gasto administrativo | J2: 10 | K2: MINUTOS | L2: 3000 | M2: 30000 | O2: =R2 -> 30000 | P2: =IF(C2="Alta Complejidad",M2,0) -> 0 | Q2: 0 | R2: =M2+(M2*Q2) -> 30000 | S2: =IFERROR(((R2-P2)/R2),0) -> 1 | T2: =IF(C2="Mediana Complejidad",M2,0) -> 0 | U2: 0 | V2: =(T2)+(T2*U2) -> 0 | W2: =IFERROR(((V2-T2)/V2),0) -> 0 | X2: =IF(C2="Baja Complejidad",M2,0) -> 0 | Y2: 0 | Z2: =(X2)+(X2*Y2) -> 0 | AA2: =IFERROR(((Z2-X2)/Z2),0) -> 0 | AB2: 0.1
A3: 2026 | B3: Mayo | C3: Gasto Administrativo | D3: Gasto Administrativo | G3: GASTO_ADMINISTRATIVO | H3: GASTO_ADMINISTRATIVO | I3: Arriendo | J3: 1 | K3: UND | L3: 2000000 | M3: 2000000 | O3: =R3 -> 2000000 | P3: =IF(C3="Alta Complejidad",M3,0) -> 0 | Q3: 0 | R3: =M3+(M3*Q3) -> 2000000 | S3: =IFERROR(((R3-P3)/R3),0) -> 1 | T3: =IF(C3="Mediana Complejidad",M3,0) -> 0 | U3: 0 | V3: =(T3)+(T3*U3) -> 0 | W3: =IFERROR(((V3-T3)/V3),0) -> 0 | X3: =IF(C3="Baja Complejidad",M3,0) -> 0 | Y3: 0 | Z3: =(X3)+(X3*Y3) -> 0 | AA3: =IFERROR(((Z3-X3)/Z3),0) -> 0 | AB3: 0.1
A4: 2026 | B4: Mayo | C4: Gasto Administrativo | D4: Gasto Administrativo | G4: GASTO_ADMINISTRATIVO | H4: GASTO_ADMINISTRATIVO | I4: Pauta Redes (google, facebook, tik tok, instagram) | J4: 1 | K4: UND | L4: 200000 | M4: 200000 | O4: =R4 -> 200000 | P4: =IF(C4="Alta Complejidad",M4,0) -> 0 | Q4: 0 | R4: =M4+(M4*Q4) -> 200000 | S4: =IFERROR(((R4-P4)/R4),0) -> 1 | T4: =IF(C4="Mediana Complejidad",M4,0) -> 0 | U4: 0 | V4: =(T4)+(T4*U4) -> 0 | W4: =IFERROR(((V4-T4)/V4),0) -> 0 | X4: =IF(C4="Baja Complejidad",M4,0) -> 0 | Y4: 0 | Z4: =(X4)+(X4*Y4) -> 0 | AA4: =IFERROR(((Z4-X4)/Z4),0) -> 0 | AB4: 0.1
A5: 2026 | B5: Junio | C5: Gasto Administrativo | D5: Gasto Administrativo | G5: GASTO_ADMINISTRATIVO | H5: GASTO_ADMINISTRATIVO | I5: Gasto administrativo | J5: 10 | K5: MINUTOS | L5: 3000 | M5: 30000 | O5: =R5 -> 30000 | P5: =IF(C5="Alta Complejidad",M5,0) -> 0 | Q5: 0 | R5: =M5+(M5*Q5) -> 30000 | S5: =IFERROR(((R5-P5)/R5),0) -> 1 | T5: =IF(C5="Mediana Complejidad",M5,0) -> 0 | U5: 0 | V5: =(T5)+(T5*U5) -> 0 | W5: =IFERROR(((V5-T5)/V5),0) -> 0 | X5: =IF(C5="Baja Complejidad",M5,0) -> 0 | Y5: 0 | Z5: =(X5)+(X5*Y5) -> 0 | AA5: =IFERROR(((Z5-X5)/Z5),0) -> 0 | AB5: 0.1
A6: 2026 | B6: Junio | C6: Gasto Administrativo | D6: Gasto Administrativo | G6: GASTO_ADMINISTRATIVO | H6: GASTO_ADMINISTRATIVO | I6: Arriendo | J6: 1 | K6: UND | L6: 2000000 | M6: 2000000 | O6: =R6 -> 2000000 | P6: =IF(C6="Alta Complejidad",M6,0) -> 0 | Q6: 0 | R6: =M6+(M6*Q6) -> 2000000 | S6: =IFERROR(((R6-P6)/R6),0) -> 1 | T6: =IF(C6="Mediana Complejidad",M6,0) -> 0 | U6: 0 | V6: =(T6)+(T6*U6) -> 0 | W6: =IFERROR(((V6-T6)/V6),0) -> 0 | X6: =IF(C6="Baja Complejidad",M6,0) -> 0 | Y6: 0 | Z6: =(X6)+(X6*Y6) -> 0 | AA6: =IFERROR(((Z6-X6)/Z6),0) -> 0 | AB6: 0.1
A7: 2026 | B7: Junio | C7: Gasto Administrativo | D7: Gasto Administrativo | G7: GASTO_ADMINISTRATIVO | H7: GASTO_ADMINISTRATIVO | I7: Pauta Redes (google, facebook, tik tok, instagram) | J7: 1 | K7: UND | L7: 200000 | M7: 200000 | O7: =R7 -> 200000 | P7: =IF(C7="Alta Complejidad",M7,0) -> 0 | Q7: 0 | R7: =M7+(M7*Q7) -> 200000 | S7: =IFERROR(((R7-P7)/R7),0) -> 1 | T7: =IF(C7="Mediana Complejidad",M7,0) -> 0 | U7: 0 | V7: =(T7)+(T7*U7) -> 0 | W7: =IFERROR(((V7-T7)/V7),0) -> 0 | X7: =IF(C7="Baja Complejidad",M7,0) -> 0 | Y7: 0 | Z7: =(X7)+(X7*Y7) -> 0 | AA7: =IFERROR(((Z7-X7)/Z7),0) -> 0 | AB7: 0.1
A8: 2026 | B8: Julio | C8: Gasto Administrativo | D8: Gasto Administrativo | G8: GASTO_ADMINISTRATIVO | H8: GASTO_ADMINISTRATIVO | I8: Gasto administrativo | J8: 10 | K8: MINUTOS | L8: 3000 | M8: 30000 | O8: =R8 -> 30000 | P8: =IF(C8="Alta Complejidad",M8,0) -> 0 | Q8: 0 | R8: =M8+(M8*Q8) -> 30000 | S8: =IFERROR(((R8-P8)/R8),0) -> 1 | T8: =IF(C8="Mediana Complejidad",M8,0) -> 0 | U8: 0 | V8: =(T8)+(T8*U8) -> 0 | W8: =IFERROR(((V8-T8)/V8),0) -> 0 | X8: =IF(C8="Baja Complejidad",M8,0) -> 0 | Y8: 0 | Z8: =(X8)+(X8*Y8) -> 0 | AA8: =IFERROR(((Z8-X8)/Z8),0) -> 0 | AB8: 0.1
A9: 2026 | B9: Julio | C9: Gasto Administrativo | D9: Gasto Administrativo | G9: GASTO_ADMINISTRATIVO | H9: GASTO_ADMINISTRATIVO | I9: Arriendo | J9: 1 | K9: UND | L9: 2000000 | M9: 2000000 | O9: =R9 -> 2000000 | P9: =IF(C9="Alta Complejidad",M9,0) -> 0 | Q9: 0 | R9: =M9+(M9*Q9) -> 2000000 | S9: =IFERROR(((R9-P9)/R9),0) -> 1 | T9: =IF(C9="Mediana Complejidad",M9,0) -> 0 | U9: 0 | V9: =(T9)+(T9*U9) -> 0 | W9: =IFERROR(((V9-T9)/V9),0) -> 0 | X9: =IF(C9="Baja Complejidad",M9,0) -> 0 | Y9: 0 | Z9: =(X9)+(X9*Y9) -> 0 | AA9: =IFERROR(((Z9-X9)/Z9),0) -> 0 | AB9: 0.1
A10: 2026 | B10: Julio | C10: Gasto Administrativo | D10: Gasto Administrativo | G10: GASTO_ADMINISTRATIVO | H10: GASTO_ADMINISTRATIVO | I10: Pauta Redes (google, facebook, tik tok, instagram) | J10: 1 | K10: UND | L10: 200000 | M10: 200000 | O10: =R10 -> 200000 | P10: =IF(C10="Alta Complejidad",M10,0) -> 0 | Q10: 0 | R10: =M10+(M10*Q10) -> 200000 | S10: =IFERROR(((R10-P10)/R10),0) -> 1 | T10: =IF(C10="Mediana Complejidad",M10,0) -> 0 | U10: 0 | V10: =(T10)+(T10*U10) -> 0 | W10: =IFERROR(((V10-T10)/V10),0) -> 0 | X10: =IF(C10="Baja Complejidad",M10,0) -> 0 | Y10: 0 | Z10: =(X10)+(X10*Y10) -> 0 | AA10: =IFERROR(((Z10-X10)/Z10),0) -> 0 | AB10: 0.1
A11: 2026 | B11: Agosto | C11: Gasto Administrativo | D11: Gasto Administrativo | G11: GASTO_ADMINISTRATIVO | H11: GASTO_ADMINISTRATIVO | I11: Gasto administrativo | J11: 10 | K11: MINUTOS | L11: 3000 | M11: 30000 | O11: =R11 -> 30000 | P11: =IF(C11="Alta Complejidad",M11,0) -> 0 | Q11: 0 | R11: =M11+(M11*Q11) -> 30000 | S11: =IFERROR(((R11-P11)/R11),0) -> 1 | T11: =IF(C11="Mediana Complejidad",M11,0) -> 0 | U11: 0 | V11: =(T11)+(T11*U11) -> 0 | W11: =IFERROR(((V11-T11)/V11),0) -> 0 | X11: =IF(C11="Baja Complejidad",M11,0) -> 0 | Y11: 0 | Z11: =(X11)+(X11*Y11) -> 0 | AA11: =IFERROR(((Z11-X11)/Z11),0) -> 0 | AB11: 0.1
A12: 2026 | B12: Agosto | C12: Gasto Administrativo | D12: Gasto Administrativo | G12: GASTO_ADMINISTRATIVO | H12: GASTO_ADMINISTRATIVO | I12: Arriendo | J12: 1 | K12: UND | L12: 2000000 | M12: 2000000 | O12: =R12 -> 2000000 | P12: =IF(C12="Alta Complejidad",M12,0) -> 0 | Q12: 0 | R12: =M12+(M12*Q12) -> 2000000 | S12: =IFERROR(((R12-P12)/R12),0) -> 1 | T12: =IF(C12="Mediana Complejidad",M12,0) -> 0 | U12: 0 | V12: =(T12)+(T12*U12) -> 0 | W12: =IFERROR(((V12-T12)/V12),0) -> 0 | X12: =IF(C12="Baja Complejidad",M12,0) -> 0 | Y12: 0 | Z12: =(X12)+(X12*Y12) -> 0 | AA12: =IFERROR(((Z12-X12)/Z12),0) -> 0 | AB12: 0.1
A13: 2026 | B13: Agosto | C13: Gasto Administrativo | D13: Gasto Administrativo | G13: GASTO_ADMINISTRATIVO | H13: GASTO_ADMINISTRATIVO | I13: Pauta Redes (google, facebook, tik tok, instagram) | J13: 1 | K13: UND | L13: 200000 | M13: 200000 | O13: =R13 -> 200000 | P13: =IF(C13="Alta Complejidad",M13,0) -> 0 | Q13: 0 | R13: =M13+(M13*Q13) -> 200000 | S13: =IFERROR(((R13-P13)/R13),0) -> 1 | T13: =IF(C13="Mediana Complejidad",M13,0) -> 0 | U13: 0 | V13: =(T13)+(T13*U13) -> 0 | W13: =IFERROR(((V13-T13)/V13),0) -> 0 | X13: =IF(C13="Baja Complejidad",M13,0) -> 0 | Y13: 0 | Z13: =(X13)+(X13*Y13) -> 0 | AA13: =IFERROR(((Z13-X13)/Z13),0) -> 0 | AB13: 0.1
... A22: 2026 | B22: Noviembre | C22: Gasto Administrativo | D22: Gasto Administrativo | G22: GASTO_ADMINISTRATIVO | H22: GASTO_ADMINISTRATIVO | I22: Pauta Redes (google, facebook, tik tok, instagram) | J22: 1 | K22: UND | L22: 200000 | M22: 200000 | O22: =R22 -> 200000 | P22: =IF(C22="Alta Complejidad",M22,0) -> 0 | Q22: 0 | R22: =M22+(M22*Q22) -> 200000 | S22: =IFERROR(((R22-P22)/R22),0) -> 1 | T22: =IF(C22="Mediana Complejidad",M22,0) -> 0 | U22: 0 | V22: =(T22)+(T22*U22) -> 0 | W22: =IFERROR(((V22-T22)/V22),0) -> 0 | X22: =IF(C22="Baja Complejidad",M22,0) -> 0 | Y22: 0 | Z22: =(X22)+(X22*Y22) -> 0 | AA22: =IFERROR(((Z22-X22)/Z22),0) -> 0 | AB22: 0.1
A23: 2026 | B23: Mayo | C23: Alta Complejidad | D23: Curación de ALTA COMPLEJIDAD | E23: G20 | G23: INSUMO | H23: INSUMO | I23: Guante examen talla M | J23: 4 | K23: UND | L23: 266 | M23: 1064 | O23: =R23 -> 1064 | P23: =IF(C23="Alta Complejidad",M23,0) -> 1064 | Q23: 0 | R23: =M23+(M23*Q23) -> 1064 | S23: =IFERROR(((R23-P23)/R23),0) -> 0 | T23: =IF(C23="Mediana Complejidad",M23,0) -> 0 | U23: 0 | V23: =(T23)+(T23*U23) -> 0 | W23: =IFERROR(((V23-T23)/V23),0) -> 0 | X23: =IF(C23="Baja Complejidad",M23,0) -> 0 | Y23: 0 | Z23: =(X23)+(X23*Y23) -> 0 | AA23: =IFERROR(((Z23-X23)/Z23),0) -> 0 | AB23: 0.1
A24: 2026 | B24: Mayo | C24: Alta Complejidad | D24: Curación de ALTA COMPLEJIDAD | E24: G68 | G24: INSUMO | H24: INSUMO | I24: Guante quirurgico esteril 7.0 | J24: 2 | K24: UND | L24: 1086.232 | M24: 2172.464 | O24: =R24 -> 2172.464 | P24: =IF(C24="Alta Complejidad",M24,0) -> 2172.464 | Q24: 0 | R24: =M24+(M24*Q24) -> 2172.464 | S24: =IFERROR(((R24-P24)/R24),0) -> 0 | T24: =IF(C24="Mediana Complejidad",M24,0) -> 0 | U24: 0 | V24: =(T24)+(T24*U24) -> 0 | W24: =IFERROR(((V24-T24)/V24),0) -> 0 | X24: =IF(C24="Baja Complejidad",M24,0) -> 0 | Y24: 0 | Z24: =(X24)+(X24*Y24) -> 0 | AA24: =IFERROR(((Z24-X24)/Z24),0) -> 0 | AB24: 0.1
A25: 2026 | B25: Mayo | C25: Alta Complejidad | D25: Curación de ALTA COMPLEJIDAD | E25: G75 | G25: INSUMO | H25: INSUMO | I25: Gasa esteril 7.5 X 7.5 sobre x 5 unid | J25: 10 | K25: UND | L25: 370 | M25: 3700 | O25: =R25 -> 3700 | P25: =IF(C25="Alta Complejidad",M25,0) -> 3700 | Q25: 0 | R25: =M25+(M25*Q25) -> 3700 | S25: =IFERROR(((R25-P25)/R25),0) -> 0 | T25: =IF(C25="Mediana Complejidad",M25,0) -> 0 | U25: 0 | V25: =(T25)+(T25*U25) -> 0 | W25: =IFERROR(((V25-T25)/V25),0) -> 0 | X25: =IF(C25="Baja Complejidad",M25,0) -> 0 | Y25: 0 | Z25: =(X25)+(X25*Y25) -> 0 | AA25: =IFERROR(((Z25-X25)/Z25),0) -> 0 | AB25: 0.1
A26: 2026 | B26: Mayo | C26: Alta Complejidad | D26: Curación de ALTA COMPLEJIDAD | E26: S60 | G26: INSUMO | H26: INSUMO | I26: Solucion Salina 0.9% Bolsa 500 ml | J26: 2 | K26: UND | L26: 2643 | M26: 5286 | O26: =R26 -> 5286 | P26: =IF(C26="Alta Complejidad",M26,0) -> 5286 | Q26: 0 | R26: =M26+(M26*Q26) -> 5286 | S26: =IFERROR(((R26-P26)/R26),0) -> 0 | T26: =IF(C26="Mediana Complejidad",M26,0) -> 0 | U26: 0 | V26: =(T26)+(T26*U26) -> 0 | W26: =IFERROR(((V26-T26)/V26),0) -> 0 | X26: =IF(C26="Baja Complejidad",M26,0) -> 0 | Y26: 0 | Z26: =(X26)+(X26*Y26) -> 0 | AA26: =IFERROR(((Z26-X26)/Z26),0) -> 0 | AB26: 0.1
A27: 2026 | B27: Mayo | C27: Alta Complejidad | D27: Curación de ALTA COMPLEJIDAD | E27: T502 | G27: INSUMO | H27: INSUMO | I27: Tapabocas Estandar 1405 | J27: 5 | K27: UND | L27: 135.66 | M27: 678.3 | O27: =R27 -> 678.3 | P27: =IF(C27="Alta Complejidad",M27,0) -> 678.3 | Q27: 0 | R27: =M27+(M27*Q27) -> 678.3 | S27: =IFERROR(((R27-P27)/R27),0) -> 0 | T27: =IF(C27="Mediana Complejidad",M27,0) -> 0 | U27: 0 | V27: =(T27)+(T27*U27) -> 0 | W27: =IFERROR(((V27-T27)/V27),0) -> 0 | X27: =IF(C27="Baja Complejidad",M27,0) -> 0 | Y27: 0 | Z27: =(X27)+(X27*Y27) -> 0 | AA27: =IFERROR(((Z27-X27)/Z27),0) -> 0 | AB27: 0.1
A28: 2026 | B28: Mayo | C28: Alta Complejidad | D28: Curación de ALTA COMPLEJIDAD | E28: B10 | G28: INSUMO | H28: INSUMO | I28: Bata Desechable con Manga No Esteril | J28: 2 | K28: UND | L28: 3808 | M28: 7616 | O28: =R28 -> 7616 | P28: =IF(C28="Alta Complejidad",M28,0) -> 7616 | Q28: 0 | R28: =M28+(M28*Q28) -> 7616 | S28: =IFERROR(((R28-P28)/R28),0) -> 0 | T28: =IF(C28="Mediana Complejidad",M28,0) -> 0 | U28: 0 | V28: =(T28)+(T28*U28) -> 0 | W28: =IFERROR(((V28-T28)/V28),0) -> 0 | X28: =IF(C28="Baja Complejidad",M28,0) -> 0 | Y28: 0 | Z28: =(X28)+(X28*Y28) -> 0 | AA28: =IFERROR(((Z28-X28)/Z28),0) -> 0 | AB28: 0.1
A29: 2026 | B29: Mayo | C29: Alta Complejidad | D29: Curación de ALTA COMPLEJIDAD | E29: G07 | G29: INSUMO | H29: INSUMO | I29: Gorro Desechable Estandar Blanco | J29: 2 | K29: UND | L29: 111.86 | M29: 223.72 | O29: =R29 -> 223.72 | P29: =IF(C29="Alta Complejidad",M29,0) -> 223.72 | Q29: 0 | R29: =M29+(M29*Q29) -> 223.72 | S29: =IFERROR(((R29-P29)/R29),0) -> 0 | T29: =IF(C29="Mediana Complejidad",M29,0) -> 0 | U29: 0 | V29: =(T29)+(T29*U29) -> 0 | W29: =IFERROR(((V29-T29)/V29),0) -> 0 | X29: =IF(C29="Baja Complejidad",M29,0) -> 0 | Y29: 0 | Z29: =(X29)+(X29*Y29) -> 0 | AA29: =IFERROR(((Z29-X29)/Z29),0) -> 0 | AB29: 0.1
A30: 2026 | B30: Mayo | C30: Alta Complejidad | D30: Curación de ALTA COMPLEJIDAD | E30: 360100 | G30: INSUMO | H30: INSUMO | I30: Granudacyn Solución 250 ml Spray | J30: 10 | K30: UND | L30: 80300 | M30: 3212 | O30: =R30 -> 3212 | P30: =IF(C30="Alta Complejidad",M30,0) -> 3212 | Q30: 0 | R30: =M30+(M30*Q30) -> 3212 | S30: =IFERROR(((R30-P30)/R30),0) -> 0 | T30: =IF(C30="Mediana Complejidad",M30,0) -> 0 | U30: 0 | V30: =(T30)+(T30*U30) -> 0 | W30: =IFERROR(((V30-T30)/V30),0) -> 0 | X30: =IF(C30="Baja Complejidad",M30,0) -> 0 | Y30: 0 | Z30: =(X30)+(X30*Y30) -> 0 | AA30: =IFERROR(((Z30-X30)/Z30),0) -> 0 | AB30: 0.1
A31: 2026 | B31: Mayo | C31: Alta Complejidad | D31: Curación de ALTA COMPLEJIDAD | E31: T180 | G31: INSUMO | H31: INSUMO | I31: Toalla de Manos Pre-cortada Natural R7 | J31: 5 | K31: UND | L31: 17888.08 | M31: 89440.4 | O31: =R31 -> 89440.4 | P31: =IF(C31="Alta Complejidad",M31,0) -> 89440.4 | Q31: 0 | R31: =M31+(M31*Q31) -> 89440.4 | S31: =IFERROR(((R31-P31)/R31),0) -> 0 | T31: =IF(C31="Mediana Complejidad",M31,0) -> 0 | U31: 0 | V31: =(T31)+(T31*U31) -> 0 | W31: =IFERROR(((V31-T31)/V31),0) -> 0 | X31: =IF(C31="Baja Complejidad",M31,0) -> 0 | Y31: 0 | Z31: =(X31)+(X31*Y31) -> 0 | AA31: =IFERROR(((Z31-X31)/Z31),0) -> 0 | AB31: 0.1
A32: 2026 | B32: Mayo | C32: Alta Complejidad | D32: Curación de ALTA COMPLEJIDAD | E32: H15 | G32: INSUMO | H32: INSUMO | I32: Hoja para bisturi 15 | J32: 2 | K32: UND | L32: 337.38379 | M32: 674.76758 | O32: =R32 -> 674.76758 | P32: =IF(C32="Alta Complejidad",M32,0) -> 674.76758 | Q32: 0 | R32: =M32+(M32*Q32) -> 674.76758 | S32: =IFERROR(((R32-P32)/R32),0) -> 0 | T32: =IF(C32="Mediana Complejidad",M32,0) -> 0 | U32: 0 | V32: =(T32)+(T32*U32) -> 0 | W32: =IFERROR(((V32-T32)/V32),0) -> 0 | X32: =IF(C32="Baja Complejidad",M32,0) -> 0 | Y32: 0 | Z32: =(X32)+(X32*Y32) -> 0 | AA32: =IFERROR(((Z32-X32)/Z32),0) -> 0 | AB32: 0.1
A33: 2026 | B33: Mayo | C33: Alta Complejidad | D33: Curación de ALTA COMPLEJIDAD | E33: 2438 | G33: INSUMO | H33: INSUMO | I33: Tubifast 10m Azul | J33: 2 | K33: UND | L33: 67900 | M33: 13580 | O33: =R33 -> 13580 | P33: =IF(C33="Alta Complejidad",M33,0) -> 13580 | Q33: 0 | R33: =M33+(M33*Q33) -> 13580 | S33: =IFERROR(((R33-P33)/R33),0) -> 0 | T33: =IF(C33="Mediana Complejidad",M33,0) -> 0 | U33: 0 | V33: =(T33)+(T33*U33) -> 0 | W33: =IFERROR(((V33-T33)/V33),0) -> 0 | X33: =IF(C33="Baja Complejidad",M33,0) -> 0 | Y33: 0 | Z33: =(X33)+(X33*Y33) -> 0 | AA33: =IFERROR(((Z33-X33)/Z33),0) -> 0 | AB33: 0.1
A34: 2026 | B34: Mayo | C34: Alta Complejidad | D34: Curación de ALTA COMPLEJIDAD | E34: 2434 | G34: INSUMO | H34: INSUMO | I34: Tubifast 10m Rojo | J34: 2 | K34: UND | L34: 50300 | M34: 10060 | O34: =R34 -> 10060 | P34: =IF(C34="Alta Complejidad",M34,0) -> 10060 | Q34: 0 | R34: =M34+(M34*Q34) -> 10060 | S34: =IFERROR(((R34-P34)/R34),0) -> 0 | T34: =IF(C34="Mediana Complejidad",M34,0) -> 0 | U34: 0 | V34: =(T34)+(T34*U34) -> 0 | W34: =IFERROR(((V34-T34)/V34),0) -> 0 | X34: =IF(C34="Baja Complejidad",M34,0) -> 0 | Y34: 0 | Z34: =(X34)+(X34*Y34) -> 0 | AA34: =IFERROR(((Z34-X34)/Z34),0) -> 0 | AB34: 0.1
A35: 2026 | B35: Mayo | C35: Alta Complejidad | D35: Curación de ALTA COMPLEJIDAD | E35: 3505 | G35: INSUMO | H35: INSUMO | I35: Setopress 10 cm x 3.5 m Relaxed x 12 | J35: 2 | K35: UND | L35: 43500 | M35: 7250 | O35: =R35 -> 7250 | P35: =IF(C35="Alta Complejidad",M35,0) -> 7250 | Q35: 0 | R35: =M35+(M35*Q35) -> 7250 | S35: =IFERROR(((R35-P35)/R35),0) -> 0 | T35: =IF(C35="Mediana Complejidad",M35,0) -> 0 | U35: 0 | V35: =(T35)+(T35*U35) -> 0 | W35: =IFERROR(((V35-T35)/V35),0) -> 0 | X35: =IF(C35="Baja Complejidad",M35,0) -> 0 | Y35: 0 | Z35: =(X35)+(X35*Y35) -> 0 | AA35: =IFERROR(((Z35-X35)/Z35),0) -> 0 | AB35: 0.1
A36: 2026 | B36: Mayo | C36: Alta Complejidad | D36: Curación de ALTA COMPLEJIDAD | F36: 1800 | G36: MANO_OBRA | H36: MANO_OBRA | I36: Enfermera | J36: 60 | K36: MINUTOS | L36: 20894.4 | M36: =+L36*J36 -> 1253664 | O36: =R36 -> 1253664 | P36: =IF(C36="Alta Complejidad",M36,0) -> 1253664 | Q36: 0 | R36: =M36+(M36*Q36) -> 1253664 | S36: =IFERROR(((R36-P36)/R36),0) -> 0 | T36: =IF(C36="Mediana Complejidad",M36,0) -> 0 | U36: 0 | V36: =(T36)+(T36*U36) -> 0 | W36: =IFERROR(((V36-T36)/V36),0) -> 0 | X36: =IF(C36="Baja Complejidad",M36,0) -> 0 | Y36: 0 | Z36: =(X36)+(X36*Y36) -> 0 | AA36: =IFERROR(((Z36-X36)/Z36),0) -> 0 | AB36: 0.1
A37: 2026 | B37: Mayo | C37: Alta Complejidad | D37: Curación de ALTA COMPLEJIDAD | F37: 900 | G37: MANO_OBRA | H37: MANO_OBRA | I37: Auxiliar enfermeria | J37: 60 | K37: MINUTOS | L37: 6048.3 | M37: =+L37*J37 -> 362898 | O37: =R37 -> 362898 | P37: =IF(C37="Alta Complejidad",M37,0) -> 362898 | Q37: 0 | R37: =M37+(M37*Q37) -> 362898 | S37: =IFERROR(((R37-P37)/R37),0) -> 0 | T37: =IF(C37="Mediana Complejidad",M37,0) -> 0 | U37: 0 | V37: =(T37)+(T37*U37) -> 0 | W37: =IFERROR(((V37-T37)/V37),0) -> 0 | X37: =IF(C37="Baja Complejidad",M37,0) -> 0 | Y37: 0 | Z37: =(X37)+(X37*Y37) -> 0 | AA37: =IFERROR(((Z37-X37)/Z37),0) -> 0 | AB37: 0.1
A38: 2026 | B38: Mayo | C38: Alta Complejidad | D38: Curación de ALTA COMPLEJIDAD | F38: 600 | G38: MANO_OBRA | H38: MANO_OBRA | I38: Cirujano vascular | J38: 60 | K38: MINUTOS | L38: 35000 | M38: =+L38*J38 -> 2100000 | O38: =R38 -> 2100000 | P38: =IF(C38="Alta Complejidad",M38,0) -> 2100000 | Q38: 0 | R38: =M38+(M38*Q38) -> 2100000 | S38: =IFERROR(((R38-P38)/R38),0) -> 0 | T38: =IF(C38="Mediana Complejidad",M38,0) -> 0 | U38: 0 | V38: =(T38)+(T38*U38) -> 0 | W38: =IFERROR(((V38-T38)/V38),0) -> 0 | X38: =IF(C38="Baja Complejidad",M38,0) -> 0 | Y38: 0 | Z38: =(X38)+(X38*Y38) -> 0 | AA38: =IFERROR(((Z38-X38)/Z38),0) -> 0 | AB38: 0.1
A39: 2026 | B39: Mayo | C39: Alta Complejidad | D39: Curación de ALTA COMPLEJIDAD | F39: 600 | G39: MANO_OBRA | H39: MANO_OBRA | I39: Nutricionista | J39: 60 | K39: MINUTOS | L39: 25000 | M39: =+L39*J39 -> 1500000 | O39: =R39 -> 1500000 | P39: =IF(C39="Alta Complejidad",M39,0) -> 1500000 | Q39: 0 | R39: =M39+(M39*Q39) -> 1500000 | S39: =IFERROR(((R39-P39)/R39),0) -> 0 | T39: =IF(C39="Mediana Complejidad",M39,0) -> 0 | U39: 0 | V39: =(T39)+(T39*U39) -> 0 | W39: =IFERROR(((V39-T39)/V39),0) -> 0 | X39: =IF(C39="Baja Complejidad",M39,0) -> 0 | Y39: 0 | Z39: =(X39)+(X39*Y39) -> 0 | AA39: =IFERROR(((Z39-X39)/Z39),0) -> 0 | AB39: 0.1
A40: 2026 | B40: Mayo | C40: Alta Complejidad | D40: Curación de ALTA COMPLEJIDAD | F40: 600 | G40: MANO_OBRA | H40: MANO_OBRA | I40: Terapeuta fisico | J40: 60 | K40: MINUTOS | L40: 20000 | M40: =+L40*J40 -> 1200000 | O40: =R40 -> 1200000 | P40: =IF(C40="Alta Complejidad",M40,0) -> 1200000 | Q40: 0 | R40: =M40+(M40*Q40) -> 1200000 | S40: =IFERROR(((R40-P40)/R40),0) -> 0 | T40: =IF(C40="Mediana Complejidad",M40,0) -> 0 | U40: 0 | V40: =(T40)+(T40*U40) -> 0 | W40: =IFERROR(((V40-T40)/V40),0) -> 0 | X40: =IF(C40="Baja Complejidad",M40,0) -> 0 | Y40: 0 | Z40: =(X40)+(X40*Y40) -> 0 | AA40: =IFERROR(((Z40-X40)/Z40),0) -> 0 | AB40: 0.1
A41: 2026 | B41: Junio | C41: Alta Complejidad | D41: Curación de ALTA COMPLEJIDAD | E41: G20 | G41: INSUMO | H41: INSUMO | I41: Guante examen talla M | J41: 4 | K41: UND | L41: 266 | M41: 1064 | O41: =R41 -> 1064 | P41: =IF(C41="Alta Complejidad",M41,0) -> 1064 | Q41: 0 | R41: =M41+(M41*Q41) -> 1064 | S41: =IFERROR(((R41-P41)/R41),0) -> 0 | T41: =IF(C41="Mediana Complejidad",M41,0) -> 0 | U41: 0 | V41: =(T41)+(T41*U41) -> 0 | W41: =IFERROR(((V41-T41)/V41),0) -> 0 | X41: =IF(C41="Baja Complejidad",M41,0) -> 0 | Y41: 0 | Z41: =(X41)+(X41*Y41) -> 0 | AA41: =IFERROR(((Z41-X41)/Z41),0) -> 0 | AB41: 0.1
A42: 2026 | B42: Junio | C42: Alta Complejidad | D42: Curación de ALTA COMPLEJIDAD | E42: G68 | G42: INSUMO | H42: INSUMO | I42: Guante quirurgico esteril 7.0 | J42: 2 | K42: UND | L42: 1086.232 | M42: 2172.464 | O42: =R42 -> 2172.464 | P42: =IF(C42="Alta Complejidad",M42,0) -> 2172.464 | Q42: 0 | R42: =M42+(M42*Q42) -> 2172.464 | S42: =IFERROR(((R42-P42)/R42),0) -> 0 | T42: =IF(C42="Mediana Complejidad",M42,0) -> 0 | U42: 0 | V42: =(T42)+(T42*U42) -> 0 | W42: =IFERROR(((V42-T42)/V42),0) -> 0 | X42: =IF(C42="Baja Complejidad",M42,0) -> 0 | Y42: 0 | Z42: =(X42)+(X42*Y42) -> 0 | AA42: =IFERROR(((Z42-X42)/Z42),0) -> 0 | AB42: 0.1
A43: 2026 | B43: Junio | C43: Alta Complejidad | D43: Curación de ALTA COMPLEJIDAD | E43: G75 | G43: INSUMO | H43: INSUMO | I43: Gasa esteril 7.5 X 7.5 sobre x 5 unid | J43: 10 | K43: UND | L43: 370 | M43: 3700 | O43: =R43 -> 3700 | P43: =IF(C43="Alta Complejidad",M43,0) -> 3700 | Q43: 0 | R43: =M43+(M43*Q43) -> 3700 | S43: =IFERROR(((R43-P43)/R43),0) -> 0 | T43: =IF(C43="Mediana Complejidad",M43,0) -> 0 | U43: 0 | V43: =(T43)+(T43*U43) -> 0 | W43: =IFERROR(((V43-T43)/V43),0) -> 0 | X43: =IF(C43="Baja Complejidad",M43,0) -> 0 | Y43: 0 | Z43: =(X43)+(X43*Y43) -> 0 | AA43: =IFERROR(((Z43-X43)/Z43),0) -> 0 | AB43: 0.1
A44: 2026 | B44: Junio | C44: Alta Complejidad | D44: Curación de ALTA COMPLEJIDAD | E44: S60 | G44: INSUMO | H44: INSUMO | I44: Solucion Salina 0.9% Bolsa 500 ml | J44: 2 | K44: UND | L44: 2643 | M44: 5286 | O44: =R44 -> 5286 | P44: =IF(C44="Alta Complejidad",M44,0) -> 5286 | Q44: 0 | R44: =M44+(M44*Q44) -> 5286 | S44: =IFERROR(((R44-P44)/R44),0) -> 0 | T44: =IF(C44="Mediana Complejidad",M44,0) -> 0 | U44: 0 | V44: =(T44)+(T44*U44) -> 0 | W44: =IFERROR(((V44-T44)/V44),0) -> 0 | X44: =IF(C44="Baja Complejidad",M44,0) -> 0 | Y44: 0 | Z44: =(X44)+(X44*Y44) -> 0 | AA44: =IFERROR(((Z44-X44)/Z44),0) -> 0 | AB44: 0.1
A45: 2026 | B45: Junio | C45: Alta Complejidad | D45: Curación de ALTA COMPLEJIDAD | E45: T502 | G45: INSUMO | H45: INSUMO | I45: Tapabocas Estandar 1405 | J45: 5 | K45: UND | L45: 135.66 | M45: 678.3 | O45: =R45 -> 678.3 | P45: =IF(C45="Alta Complejidad",M45,0) -> 678.3 | Q45: 0 | R45: =M45+(M45*Q45) -> 678.3 | S45: =IFERROR(((R45-P45)/R45),0) -> 0 | T45: =IF(C45="Mediana Complejidad",M45,0) -> 0 | U45: 0 | V45: =(T45)+(T45*U45) -> 0 | W45: =IFERROR(((V45-T45)/V45),0) -> 0 | X45: =IF(C45="Baja Complejidad",M45,0) -> 0 | Y45: 0 | Z45: =(X45)+(X45*Y45) -> 0 | AA45: =IFERROR(((Z45-X45)/Z45),0) -> 0 | AB45: 0.1
A46: 2026 | B46: Junio | C46: Alta Complejidad | D46: Curación de ALTA COMPLEJIDAD | E46: B10 | G46: INSUMO | H46: INSUMO | I46: Bata Desechable con Manga No Esteril | J46: 2 | K46: UND | L46: 3808 | M46: 7616 | O46: =R46 -> 7616 | P46: =IF(C46="Alta Complejidad",M46,0) -> 7616 | Q46: 0 | R46: =M46+(M46*Q46) -> 7616 | S46: =IFERROR(((R46-P46)/R46),0) -> 0 | T46: =IF(C46="Mediana Complejidad",M46,0) -> 0 | U46: 0 | V46: =(T46)+(T46*U46) -> 0 | W46: =IFERROR(((V46-T46)/V46),0) -> 0 | X46: =IF(C46="Baja Complejidad",M46,0) -> 0 | Y46: 0 | Z46: =(X46)+(X46*Y46) -> 0 | AA46: =IFERROR(((Z46-X46)/Z46),0) -> 0 | AB46: 0.1
A47: 2026 | B47: Junio | C47: Alta Complejidad | D47: Curación de ALTA COMPLEJIDAD | E47: G07 | G47: INSUMO | H47: INSUMO | I47: Gorro Desechable Estandar Blanco | J47: 2 | K47: UND | L47: 111.86 | M47: 223.72 | O47: =R47 -> 223.72 | P47: =IF(C47="Alta Complejidad",M47,0) -> 223.72 | Q47: 0 | R47: =M47+(M47*Q47) -> 223.72 | S47: =IFERROR(((R47-P47)/R47),0) -> 0 | T47: =IF(C47="Mediana Complejidad",M47,0) -> 0 | U47: 0 | V47: =(T47)+(T47*U47) -> 0 | W47: =IFERROR(((V47-T47)/V47),0) -> 0 | X47: =IF(C47="Baja Complejidad",M47,0) -> 0 | Y47: 0 | Z47: =(X47)+(X47*Y47) -> 0 | AA47: =IFERROR(((Z47-X47)/Z47),0) -> 0 | AB47: 0.1
A48: 2026 | B48: Junio | C48: Alta Complejidad | D48: Curación de ALTA COMPLEJIDAD | E48: 360100 | G48: INSUMO | H48: INSUMO | I48: Granudacyn Solución 250 ml Spray | J48: 10 | K48: UND | L48: 80300 | M48: 3212 | O48: =R48 -> 3212 | P48: =IF(C48="Alta Complejidad",M48,0) -> 3212 | Q48: 0 | R48: =M48+(M48*Q48) -> 3212 | S48: =IFERROR(((R48-P48)/R48),0) -> 0 | T48: =IF(C48="Mediana Complejidad",M48,0) -> 0 | U48: 0 | V48: =(T48)+(T48*U48) -> 0 | W48: =IFERROR(((V48-T48)/V48),0) -> 0 | X48: =IF(C48="Baja Complejidad",M48,0) -> 0 | Y48: 0 | Z48: =(X48)+(X48*Y48) -> 0 | AA48: =IFERROR(((Z48-X48)/Z48),0) -> 0 | AB48: 0.1
A49: 2026 | B49: Junio | C49: Alta Complejidad | D49: Curación de ALTA COMPLEJIDAD | E49: T180 | G49: INSUMO | H49: INSUMO | I49: Toalla de Manos Pre-cortada Natural R7 | J49: 5 | K49: UND | L49: 17888.08 | M49: 89440.4 | O49: =R49 -> 89440.4 | P49: =IF(C49="Alta Complejidad",M49,0) -> 89440.4 | Q49: 0 | R49: =M49+(M49*Q49) -> 89440.4 | S49: =IFERROR(((R49-P49)/R49),0) -> 0 | T49: =IF(C49="Mediana Complejidad",M49,0) -> 0 | U49: 0 | V49: =(T49)+(T49*U49) -> 0 | W49: =IFERROR(((V49-T49)/V49),0) -> 0 | X49: =IF(C49="Baja Complejidad",M49,0) -> 0 | Y49: 0 | Z49: =(X49)+(X49*Y49) -> 0 | AA49: =IFERROR(((Z49-X49)/Z49),0) -> 0 | AB49: 0.1
A50: 2026 | B50: Junio | C50: Alta Complejidad | D50: Curación de ALTA COMPLEJIDAD | E50: H15 | G50: INSUMO | H50: INSUMO | I50: Hoja para bisturi 15 | J50: 2 | K50: UND | L50: 337.38379 | M50: 674.76758 | O50: =R50 -> 674.76758 | P50: =IF(C50="Alta Complejidad",M50,0) -> 674.76758 | Q50: 0 | R50: =M50+(M50*Q50) -> 674.76758 | S50: =IFERROR(((R50-P50)/R50),0) -> 0 | T50: =IF(C50="Mediana Complejidad",M50,0) -> 0 | U50: 0 | V50: =(T50)+(T50*U50) -> 0 | W50: =IFERROR(((V50-T50)/V50),0) -> 0 | X50: =IF(C50="Baja Complejidad",M50,0) -> 0 | Y50: 0 | Z50: =(X50)+(X50*Y50) -> 0 | AA50: =IFERROR(((Z50-X50)/Z50),0) -> 0 | AB50: 0.1
A51: 2026 | B51: Junio | C51: Alta Complejidad | D51: Curación de ALTA COMPLEJIDAD | E51: 2438 | G51: INSUMO | H51: INSUMO | I51: Tubifast 10m Azul | J51: 2 | K51: UND | L51: 67900 | M51: 13580 | O51: =R51 -> 13580 | P51: =IF(C51="Alta Complejidad",M51,0) -> 13580 | Q51: 0 | R51: =M51+(M51*Q51) -> 13580 | S51: =IFERROR(((R51-P51)/R51),0) -> 0 | T51: =IF(C51="Mediana Complejidad",M51,0) -> 0 | U51: 0 | V51: =(T51)+(T51*U51) -> 0 | W51: =IFERROR(((V51-T51)/V51),0) -> 0 | X51: =IF(C51="Baja Complejidad",M51,0) -> 0 | Y51: 0 | Z51: =(X51)+(X51*Y51) -> 0 | AA51: =IFERROR(((Z51-X51)/Z51),0) -> 0 | AB51: 0.1
A52: 2026 | B52: Junio | C52: Alta Complejidad | D52: Curación de ALTA COMPLEJIDAD | E52: 2434 | G52: INSUMO | H52: INSUMO | I52: Tubifast 10m Rojo | J52: 2 | K52: UND | L52: 50300 | M52: 10060 | O52: =R52 -> 10060 | P52: =IF(C52="Alta Complejidad",M52,0) -> 10060 | Q52: 0 | R52: =M52+(M52*Q52) -> 10060 | S52: =IFERROR(((R52-P52)/R52),0) -> 0 | T52: =IF(C52="Mediana Complejidad",M52,0) -> 0 | U52: 0 | V52: =(T52)+(T52*U52) -> 0 | W52: =IFERROR(((V52-T52)/V52),0) -> 0 | X52: =IF(C52="Baja Complejidad",M52,0) -> 0 | Y52: 0 | Z52: =(X52)+(X52*Y52) -> 0 | AA52: =IFERROR(((Z52-X52)/Z52),0) -> 0 | AB52: 0.1
A53: 2026 | B53: Junio | C53: Alta Complejidad | D53: Curación de ALTA COMPLEJIDAD | E53: 3505 | G53: INSUMO | H53: INSUMO | I53: Setopress 10 cm x 3.5 m Relaxed x 12 | J53: 2 | K53: UND | L53: 43500 | M53: 7250 | O53: =R53 -> 7250 | P53: =IF(C53="Alta Complejidad",M53,0) -> 7250 | Q53: 0 | R53: =M53+(M53*Q53) -> 7250 | S53: =IFERROR(((R53-P53)/R53),0) -> 0 | T53: =IF(C53="Mediana Complejidad",M53,0) -> 0 | U53: 0 | V53: =(T53)+(T53*U53) -> 0 | W53: =IFERROR(((V53-T53)/V53),0) -> 0 | X53: =IF(C53="Baja Complejidad",M53,0) -> 0 | Y53: 0 | Z53: =(X53)+(X53*Y53) -> 0 | AA53: =IFERROR(((Z53-X53)/Z53),0) -> 0 | AB53: 0.1
A54: 2026 | B54: Junio | C54: Alta Complejidad | D54: Curación de ALTA COMPLEJIDAD | F54: 1800 | G54: MANO_OBRA | H54: MANO_OBRA | I54: Enfermera | J54: 60 | K54: MINUTOS | L54: 20894.4 | M54: =+L54*J54 -> 1253664 | O54: =R54 -> 1253664 | P54: =IF(C54="Alta Complejidad",M54,0) -> 1253664 | Q54: 0 | R54: =M54+(M54*Q54) -> 1253664 | S54: =IFERROR(((R54-P54)/R54),0) -> 0 | T54: =IF(C54="Mediana Complejidad",M54,0) -> 0 | U54: 0 | V54: =(T54)+(T54*U54) -> 0 | W54: =IFERROR(((V54-T54)/V54),0) -> 0 | X54: =IF(C54="Baja Complejidad",M54,0) -> 0 | Y54: 0 | Z54: =(X54)+(X54*Y54) -> 0 | AA54: =IFERROR(((Z54-X54)/Z54),0) -> 0 | AB54: 0.1
A55: 2026 | B55: Junio | C55: Alta Complejidad | D55: Curación de ALTA COMPLEJIDAD | F55: 900 | G55: MANO_OBRA | H55: MANO_OBRA | I55: Auxiliar enfermeria | J55: 60 | K55: MINUTOS | L55: 6048.3 | M55: =+L55*J55 -> 362898 | O55: =R55 -> 362898 | P55: =IF(C55="Alta Complejidad",M55,0) -> 362898 | Q55: 0 | R55: =M55+(M55*Q55) -> 362898 | S55: =IFERROR(((R55-P55)/R55),0) -> 0 | T55: =IF(C55="Mediana Complejidad",M55,0) -> 0 | U55: 0 | V55: =(T55)+(T55*U55) -> 0 | W55: =IFERROR(((V55-T55)/V55),0) -> 0 | X55: =IF(C55="Baja Complejidad",M55,0) -> 0 | Y55: 0 | Z55: =(X55)+(X55*Y55) -> 0 | AA55: =IFERROR(((Z55-X55)/Z55),0) -> 0 | AB55: 0.1
A56: 2026 | B56: Junio | C56: Alta Complejidad | D56: Curación de ALTA COMPLEJIDAD | F56: 600 | G56: MANO_OBRA | H56: MANO_OBRA | I56: Cirujano vascular | J56: 60 | K56: MINUTOS | L56: 35000 | M56: =+L56*J56 -> 2100000 | O56: =R56 -> 2100000 | P56: =IF(C56="Alta Complejidad",M56,0) -> 2100000 | Q56: 0 | R56: =M56+(M56*Q56) -> 2100000 | S56: =IFERROR(((R56-P56)/R56),0) -> 0 | T56: =IF(C56="Mediana Complejidad",M56,0) -> 0 | U56: 0 | V56: =(T56)+(T56*U56) -> 0 | W56: =IFERROR(((V56-T56)/V56),0) -> 0 | X56: =IF(C56="Baja Complejidad",M56,0) -> 0 | Y56: 0 | Z56: =(X56)+(X56*Y56) -> 0 | AA56: =IFERROR(((Z56-X56)/Z56),0) -> 0 | AB56: 0.1
A57: 2026 | B57: Junio | C57: Alta Complejidad | D57: Curación de ALTA COMPLEJIDAD | F57: 600 | G57: MANO_OBRA | H57: MANO_OBRA | I57: Nutricionista | J57: 60 | K57: MINUTOS | L57: 25000 | M57: =+L57*J57 -> 1500000 | O57: =R57 -> 1500000 | P57: =IF(C57="Alta Complejidad",M57,0) -> 1500000 | Q57: 0 | R57: =M57+(M57*Q57) -> 1500000 | S57: =IFERROR(((R57-P57)/R57),0) -> 0 | T57: =IF(C57="Mediana Complejidad",M57,0) -> 0 | U57: 0 | V57: =(T57)+(T57*U57) -> 0 | W57: =IFERROR(((V57-T57)/V57),0) -> 0 | X57: =IF(C57="Baja Complejidad",M57,0) -> 0 | Y57: 0 | Z57: =(X57)+(X57*Y57) -> 0 | AA57: =IFERROR(((Z57-X57)/Z57),0) -> 0 | AB57: 0.1
A58: 2026 | B58: Junio | C58: Alta Complejidad | D58: Curación de ALTA COMPLEJIDAD | F58: 600 | G58: MANO_OBRA | H58: MANO_OBRA | I58: Terapeuta fisico | J58: 60 | K58: MINUTOS | L58: 20000 | M58: =+L58*J58 -> 1200000 | O58: =R58 -> 1200000 | P58: =IF(C58="Alta Complejidad",M58,0) -> 1200000 | Q58: 0 | R58: =M58+(M58*Q58) -> 1200000 | S58: =IFERROR(((R58-P58)/R58),0) -> 0 | T58: =IF(C58="Mediana Complejidad",M58,0) -> 0 | U58: 0 | V58: =(T58)+(T58*U58) -> 0 | W58: =IFERROR(((V58-T58)/V58),0) -> 0 | X58: =IF(C58="Baja Complejidad",M58,0) -> 0 | Y58: 0 | Z58: =(X58)+(X58*Y58) -> 0 | AA58: =IFERROR(((Z58-X58)/Z58),0) -> 0 | AB58: 0.1
A59: 2026 | B59: Julio | C59: Alta Complejidad | D59: Curación de ALTA COMPLEJIDAD | E59: G20 | G59: INSUMO | H59: INSUMO | I59: Guante examen talla M | J59: 4 | K59: UND | L59: 266 | M59: 1064 | O59: =R59 -> 1064 | P59: =IF(C59="Alta Complejidad",M59,0) -> 1064 | Q59: 0 | R59: =M59+(M59*Q59) -> 1064 | S59: =IFERROR(((R59-P59)/R59),0) -> 0 | T59: =IF(C59="Mediana Complejidad",M59,0) -> 0 | U59: 0 | V59: =(T59)+(T59*U59) -> 0 | W59: =IFERROR(((V59-T59)/V59),0) -> 0 | X59: =IF(C59="Baja Complejidad",M59,0) -> 0 | Y59: 0 | Z59: =(X59)+(X59*Y59) -> 0 | AA59: =IFERROR(((Z59-X59)/Z59),0) -> 0 | AB59: 0.1
A60: 2026 | B60: Julio | C60: Alta Complejidad | D60: Curación de ALTA COMPLEJIDAD | E60: G68 | G60: INSUMO | H60: INSUMO | I60: Guante quirurgico esteril 7.0 | J60: 2 | K60: UND | L60: 1086.232 | M60: 2172.464 | O60: =R60 -> 2172.464 | P60: =IF(C60="Alta Complejidad",M60,0) -> 2172.464 | Q60: 0 | R60: =M60+(M60*Q60) -> 2172.464 | S60: =IFERROR(((R60-P60)/R60),0) -> 0 | T60: =IF(C60="Mediana Complejidad",M60,0) -> 0 | U60: 0 | V60: =(T60)+(T60*U60) -> 0 | W60: =IFERROR(((V60-T60)/V60),0) -> 0 | X60: =IF(C60="Baja Complejidad",M60,0) -> 0 | Y60: 0 | Z60: =(X60)+(X60*Y60) -> 0 | AA60: =IFERROR(((Z60-X60)/Z60),0) -> 0 | AB60: 0.1
A61: 2026 | B61: Julio | C61: Alta Complejidad | D61: Curación de ALTA COMPLEJIDAD | E61: G75 | G61: INSUMO | H61: INSUMO | I61: Gasa esteril 7.5 X 7.5 sobre x 5 unid | J61: 10 | K61: UND | L61: 370 | M61: 3700 | O61: =R61 -> 3700 | P61: =IF(C61="Alta Complejidad",M61,0) -> 3700 | Q61: 0 | R61: =M61+(M61*Q61) -> 3700 | S61: =IFERROR(((R61-P61)/R61),0) -> 0 | T61: =IF(C61="Mediana Complejidad",M61,0) -> 0 | U61: 0 | V61: =(T61)+(T61*U61) -> 0 | W61: =IFERROR(((V61-T61)/V61),0) -> 0 | X61: =IF(C61="Baja Complejidad",M61,0) -> 0 | Y61: 0 | Z61: =(X61)+(X61*Y61) -> 0 | AA61: =IFERROR(((Z61-X61)/Z61),0) -> 0 | AB61: 0.1
A62: 2026 | B62: Julio | C62: Alta Complejidad | D62: Curación de ALTA COMPLEJIDAD | E62: S60 | G62: INSUMO | H62: INSUMO | I62: Solucion Salina 0.9% Bolsa 500 ml | J62: 2 | K62: UND | L62: 2643 | M62: 5286 | O62: =R62 -> 5286 | P62: =IF(C62="Alta Complejidad",M62,0) -> 5286 | Q62: 0 | R62: =M62+(M62*Q62) -> 5286 | S62: =IFERROR(((R62-P62)/R62),0) -> 0 | T62: =IF(C62="Mediana Complejidad",M62,0) -> 0 | U62: 0 | V62: =(T62)+(T62*U62) -> 0 | W62: =IFERROR(((V62-T62)/V62),0) -> 0 | X62: =IF(C62="Baja Complejidad",M62,0) -> 0 | Y62: 0 | Z62: =(X62)+(X62*Y62) -> 0 | AA62: =IFERROR(((Z62-X62)/Z62),0) -> 0 | AB62: 0.1
A63: 2026 | B63: Julio | C63: Alta Complejidad | D63: Curación de ALTA COMPLEJIDAD | E63: T502 | G63: INSUMO | H63: INSUMO | I63: Tapabocas Estandar 1405 | J63: 5 | K63: UND | L63: 135.66 | M63: 678.3 | O63: =R63 -> 678.3 | P63: =IF(C63="Alta Complejidad",M63,0) -> 678.3 | Q63: 0 | R63: =M63+(M63*Q63) -> 678.3 | S63: =IFERROR(((R63-P63)/R63),0) -> 0 | T63: =IF(C63="Mediana Complejidad",M63,0) -> 0 | U63: 0 | V63: =(T63)+(T63*U63) -> 0 | W63: =IFERROR(((V63-T63)/V63),0) -> 0 | X63: =IF(C63="Baja Complejidad",M63,0) -> 0 | Y63: 0 | Z63: =(X63)+(X63*Y63) -> 0 | AA63: =IFERROR(((Z63-X63)/Z63),0) -> 0 | AB63: 0.1
A64: 2026 | B64: Julio | C64: Alta Complejidad | D64: Curación de ALTA COMPLEJIDAD | E64: B10 | G64: INSUMO | H64: INSUMO | I64: Bata Desechable con Manga No Esteril | J64: 2 | K64: UND | L64: 3808 | M64: 7616 | O64: =R64 -> 7616 | P64: =IF(C64="Alta Complejidad",M64,0) -> 7616 | Q64: 0 | R64: =M64+(M64*Q64) -> 7616 | S64: =IFERROR(((R64-P64)/R64),0) -> 0 | T64: =IF(C64="Mediana Complejidad",M64,0) -> 0 | U64: 0 | V64: =(T64)+(T64*U64) -> 0 | W64: =IFERROR(((V64-T64)/V64),0) -> 0 | X64: =IF(C64="Baja Complejidad",M64,0) -> 0 | Y64: 0 | Z64: =(X64)+(X64*Y64) -> 0 | AA64: =IFERROR(((Z64-X64)/Z64),0) -> 0 | AB64: 0.1
A65: 2026 | B65: Julio | C65: Alta Complejidad | D65: Curación de ALTA COMPLEJIDAD | E65: G07 | G65: INSUMO | H65: INSUMO | I65: Gorro Desechable Estandar Blanco | J65: 2 | K65: UND | L65: 111.86 | M65: 223.72 | O65: =R65 -> 223.72 | P65: =IF(C65="Alta Complejidad",M65,0) -> 223.72 | Q65: 0 | R65: =M65+(M65*Q65) -> 223.72 | S65: =IFERROR(((R65-P65)/R65),0) -> 0 | T65: =IF(C65="Mediana Complejidad",M65,0) -> 0 | U65: 0 | V65: =(T65)+(T65*U65) -> 0 | W65: =IFERROR(((V65-T65)/V65),0) -> 0 | X65: =IF(C65="Baja Complejidad",M65,0) -> 0 | Y65: 0 | Z65: =(X65)+(X65*Y65) -> 0 | AA65: =IFERROR(((Z65-X65)/Z65),0) -> 0 | AB65: 0.1
A66: 2026 | B66: Julio | C66: Alta Complejidad | D66: Curación de ALTA COMPLEJIDAD | E66: 360100 | G66: INSUMO | H66: INSUMO | I66: Granudacyn Solución 250 ml Spray | J66: 10 | K66: UND | L66: 80300 | M66: 3212 | O66: =R66 -> 3212 | P66: =IF(C66="Alta Complejidad",M66,0) -> 3212 | Q66: 0 | R66: =M66+(M66*Q66) -> 3212 | S66: =IFERROR(((R66-P66)/R66),0) -> 0 | T66: =IF(C66="Mediana Complejidad",M66,0) -> 0 | U66: 0 | V66: =(T66)+(T66*U66) -> 0 | W66: =IFERROR(((V66-T66)/V66),0) -> 0 | X66: =IF(C66="Baja Complejidad",M66,0) -> 0 | Y66: 0 | Z66: =(X66)+(X66*Y66) -> 0 | AA66: =IFERROR(((Z66-X66)/Z66),0) -> 0 | AB66: 0.1
A67: 2026 | B67: Julio | C67: Alta Complejidad | D67: Curación de ALTA COMPLEJIDAD | E67: T180 | G67: INSUMO | H67: INSUMO | I67: Toalla de Manos Pre-cortada Natural R7 | J67: 5 | K67: UND | L67: 17888.08 | M67: 89440.4 | O67: =R67 -> 89440.4 | P67: =IF(C67="Alta Complejidad",M67,0) -> 89440.4 | Q67: 0 | R67: =M67+(M67*Q67) -> 89440.4 | S67: =IFERROR(((R67-P67)/R67),0) -> 0 | T67: =IF(C67="Mediana Complejidad",M67,0) -> 0 | U67: 0 | V67: =(T67)+(T67*U67) -> 0 | W67: =IFERROR(((V67-T67)/V67),0) -> 0 | X67: =IF(C67="Baja Complejidad",M67,0) -> 0 | Y67: 0 | Z67: =(X67)+(X67*Y67) -> 0 | AA67: =IFERROR(((Z67-X67)/Z67),0) -> 0 | AB67: 0.1
A68: 2026 | B68: Julio | C68: Alta Complejidad | D68: Curación de ALTA COMPLEJIDAD | E68: H15 | G68: INSUMO | H68: INSUMO | I68: Hoja para bisturi 15 | J68: 2 | K68: UND | L68: 337.38379 | M68: 674.76758 | O68: =R68 -> 674.76758 | P68: =IF(C68="Alta Complejidad",M68,0) -> 674.76758 | Q68: 0 | R68: =M68+(M68*Q68) -> 674.76758 | S68: =IFERROR(((R68-P68)/R68),0) -> 0 | T68: =IF(C68="Mediana Complejidad",M68,0) -> 0 | U68: 0 | V68: =(T68)+(T68*U68) -> 0 | W68: =IFERROR(((V68-T68)/V68),0) -> 0 | X68: =IF(C68="Baja Complejidad",M68,0) -> 0 | Y68: 0 | Z68: =(X68)+(X68*Y68) -> 0 | AA68: =IFERROR(((Z68-X68)/Z68),0) -> 0 | AB68: 0.1
A69: 2026 | B69: Julio | C69: Alta Complejidad | D69: Curación de ALTA COMPLEJIDAD | E69: 2438 | G69: INSUMO | H69: INSUMO | I69: Tubifast 10m Azul | J69: 2 | K69: UND | L69: 67900 | M69: 13580 | O69: =R69 -> 13580 | P69: =IF(C69="Alta Complejidad",M69,0) -> 13580 | Q69: 0 | R69: =M69+(M69*Q69) -> 13580 | S69: =IFERROR(((R69-P69)/R69),0) -> 0 | T69: =IF(C69="Mediana Complejidad",M69,0) -> 0 | U69: 0 | V69: =(T69)+(T69*U69) -> 0 | W69: =IFERROR(((V69-T69)/V69),0) -> 0 | X69: =IF(C69="Baja Complejidad",M69,0) -> 0 | Y69: 0 | Z69: =(X69)+(X69*Y69) -> 0 | AA69: =IFERROR(((Z69-X69)/Z69),0) -> 0 | AB69: 0.1
A70: 2026 | B70: Julio | C70: Alta Complejidad | D70: Curación de ALTA COMPLEJIDAD | E70: 2434 | G70: INSUMO | H70: INSUMO | I70: Tubifast 10m Rojo | J70: 2 | K70: UND | L70: 50300 | M70: 10060 | O70: =R70 -> 10060 | P70: =IF(C70="Alta Complejidad",M70,0) -> 10060 | Q70: 0 | R70: =M70+(M70*Q70) -> 10060 | S70: =IFERROR(((R70-P70)/R70),0) -> 0 | T70: =IF(C70="Mediana Complejidad",M70,0) -> 0 | U70: 0 | V70: =(T70)+(T70*U70) -> 0 | W70: =IFERROR(((V70-T70)/V70),0) -> 0 | X70: =IF(C70="Baja Complejidad",M70,0) -> 0 | Y70: 0 | Z70: =(X70)+(X70*Y70) -> 0 | AA70: =IFERROR(((Z70-X70)/Z70),0) -> 0 | AB70: 0.1
A71: 2026 | B71: Julio | C71: Alta Complejidad | D71: Curación de ALTA COMPLEJIDAD | E71: 3505 | G71: INSUMO | H71: INSUMO | I71: Setopress 10 cm x 3.5 m Relaxed x 12 | J71: 2 | K71: UND | L71: 43500 | M71: 7250 | O71: =R71 -> 7250 | P71: =IF(C71="Alta Complejidad",M71,0) -> 7250 | Q71: 0 | R71: =M71+(M71*Q71) -> 7250 | S71: =IFERROR(((R71-P71)/R71),0) -> 0 | T71: =IF(C71="Mediana Complejidad",M71,0) -> 0 | U71: 0 | V71: =(T71)+(T71*U71) -> 0 | W71: =IFERROR(((V71-T71)/V71),0) -> 0 | X71: =IF(C71="Baja Complejidad",M71,0) -> 0 | Y71: 0 | Z71: =(X71)+(X71*Y71) -> 0 | AA71: =IFERROR(((Z71-X71)/Z71),0) -> 0 | AB71: 0.1
A72: 2026 | B72: Julio | C72: Alta Complejidad | D72: Curación de ALTA COMPLEJIDAD | F72: 1800 | G72: MANO_OBRA | H72: MANO_OBRA | I72: Enfermera | J72: 60 | K72: MINUTOS | L72: 20894.4 | M72: =+L72*J72 -> 1253664 | O72: =R72 -> 1253664 | P72: =IF(C72="Alta Complejidad",M72,0) -> 1253664 | Q72: 0 | R72: =M72+(M72*Q72) -> 1253664 | S72: =IFERROR(((R72-P72)/R72),0) -> 0 | T72: =IF(C72="Mediana Complejidad",M72,0) -> 0 | U72: 0 | V72: =(T72)+(T72*U72) -> 0 | W72: =IFERROR(((V72-T72)/V72),0) -> 0 | X72: =IF(C72="Baja Complejidad",M72,0) -> 0 | Y72: 0 | Z72: =(X72)+(X72*Y72) -> 0 | AA72: =IFERROR(((Z72-X72)/Z72),0) -> 0 | AB72: 0.1
A73: 2026 | B73: Julio | C73: Alta Complejidad | D73: Curación de ALTA COMPLEJIDAD | F73: 900 | G73: MANO_OBRA | H73: MANO_OBRA | I73: Auxiliar enfermeria | J73: 60 | K73: MINUTOS | L73: 6048.3 | M73: =+L73*J73 -> 362898 | O73: =R73 -> 362898 | P73: =IF(C73="Alta Complejidad",M73,0) -> 362898 | Q73: 0 | R73: =M73+(M73*Q73) -> 362898 | S73: =IFERROR(((R73-P73)/R73),0) -> 0 | T73: =IF(C73="Mediana Complejidad",M73,0) -> 0 | U73: 0 | V73: =(T73)+(T73*U73) -> 0 | W73: =IFERROR(((V73-T73)/V73),0) -> 0 | X73: =IF(C73="Baja Complejidad",M73,0) -> 0 | Y73: 0 | Z73: =(X73)+(X73*Y73) -> 0 | AA73: =IFERROR(((Z73-X73)/Z73),0) -> 0 | AB73: 0.1
A74: 2026 | B74: Julio | C74: Alta Complejidad | D74: Curación de ALTA COMPLEJIDAD | F74: 600 | G74: MANO_OBRA | H74: MANO_OBRA | I74: Cirujano vascular | J74: 60 | K74: MINUTOS | L74: 35000 | M74: =+L74*J74 -> 2100000 | O74: =R74 -> 2100000 | P74: =IF(C74="Alta Complejidad",M74,0) -> 2100000 | Q74: 0 | R74: =M74+(M74*Q74) -> 2100000 | S74: =IFERROR(((R74-P74)/R74),0) -> 0 | T74: =IF(C74="Mediana Complejidad",M74,0) -> 0 | U74: 0 | V74: =(T74)+(T74*U74) -> 0 | W74: =IFERROR(((V74-T74)/V74),0) -> 0 | X74: =IF(C74="Baja Complejidad",M74,0) -> 0 | Y74: 0 | Z74: =(X74)+(X74*Y74) -> 0 | AA74: =IFERROR(((Z74-X74)/Z74),0) -> 0 | AB74: 0.1
A75: 2026 | B75: Julio | C75: Alta Complejidad | D75: Curación de ALTA COMPLEJIDAD | F75: 600 | G75: MANO_OBRA | H75: MANO_OBRA | I75: Nutricionista | J75: 60 | K75: MINUTOS | L75: 25000 | M75: =+L75*J75 -> 1500000 | O75: =R75 -> 1500000 | P75: =IF(C75="Alta Complejidad",M75,0) -> 1500000 | Q75: 0 | R75: =M75+(M75*Q75) -> 1500000 | S75: =IFERROR(((R75-P75)/R75),0) -> 0 | T75: =IF(C75="Mediana Complejidad",M75,0) -> 0 | U75: 0 | V75: =(T75)+(T75*U75) -> 0 | W75: =IFERROR(((V75-T75)/V75),0) -> 0 | X75: =IF(C75="Baja Complejidad",M75,0) -> 0 | Y75: 0 | Z75: =(X75)+(X75*Y75) -> 0 | AA75: =IFERROR(((Z75-X75)/Z75),0) -> 0 | AB75: 0.1
A76: 2026 | B76: Julio | C76: Alta Complejidad | D76: Curación de ALTA COMPLEJIDAD | F76: 600 | G76: MANO_OBRA | H76: MANO_OBRA | I76: Terapeuta fisico | J76: 60 | K76: MINUTOS | L76: 20000 | M76: =+L76*J76 -> 1200000 | O76: =R76 -> 1200000 | P76: =IF(C76="Alta Complejidad",M76,0) -> 1200000 | Q76: 0 | R76: =M76+(M76*Q76) -> 1200000 | S76: =IFERROR(((R76-P76)/R76),0) -> 0 | T76: =IF(C76="Mediana Complejidad",M76,0) -> 0 | U76: 0 | V76: =(T76)+(T76*U76) -> 0 | W76: =IFERROR(((V76-T76)/V76),0) -> 0 | X76: =IF(C76="Baja Complejidad",M76,0) -> 0 | Y76: 0 | Z76: =(X76)+(X76*Y76) -> 0 | AA76: =IFERROR(((Z76-X76)/Z76),0) -> 0 | AB76: 0.1
A77: 2026 | B77: Agosto | C77: Alta Complejidad | D77: Curación de ALTA COMPLEJIDAD | E77: G20 | G77: INSUMO | H77: INSUMO | I77: Guante examen talla M | J77: 4 | K77: UND | L77: 266 | M77: 1064 | O77: =R77 -> 1064 | P77: =IF(C77="Alta Complejidad",M77,0) -> 1064 | Q77: 0 | R77: =M77+(M77*Q77) -> 1064 | S77: =IFERROR(((R77-P77)/R77),0) -> 0 | T77: =IF(C77="Mediana Complejidad",M77,0) -> 0 | U77: 0 | V77: =(T77)+(T77*U77) -> 0 | W77: =IFERROR(((V77-T77)/V77),0) -> 0 | X77: =IF(C77="Baja Complejidad",M77,0) -> 0 | Y77: 0 | Z77: =(X77)+(X77*Y77) -> 0 | AA77: =IFERROR(((Z77-X77)/Z77),0) -> 0 | AB77: 0.1
A78: 2026 | B78: Agosto | C78: Alta Complejidad | D78: Curación de ALTA COMPLEJIDAD | E78: G68 | G78: INSUMO | H78: INSUMO | I78: Guante quirurgico esteril 7.0 | J78: 2 | K78: UND | L78: 1086.232 | M78: 2172.464 | O78: =R78 -> 2172.464 | P78: =IF(C78="Alta Complejidad",M78,0) -> 2172.464 | Q78: 0 | R78: =M78+(M78*Q78) -> 2172.464 | S78: =IFERROR(((R78-P78)/R78),0) -> 0 | T78: =IF(C78="Mediana Complejidad",M78,0) -> 0 | U78: 0 | V78: =(T78)+(T78*U78) -> 0 | W78: =IFERROR(((V78-T78)/V78),0) -> 0 | X78: =IF(C78="Baja Complejidad",M78,0) -> 0 | Y78: 0 | Z78: =(X78)+(X78*Y78) -> 0 | AA78: =IFERROR(((Z78-X78)/Z78),0) -> 0 | AB78: 0.1
A79: 2026 | B79: Agosto | C79: Alta Complejidad | D79: Curación de ALTA COMPLEJIDAD | E79: G75 | G79: INSUMO | H79: INSUMO | I79: Gasa esteril 7.5 X 7.5 sobre x 5 unid | J79: 10 | K79: UND | L79: 370 | M79: 3700 | O79: =R79 -> 3700 | P79: =IF(C79="Alta Complejidad",M79,0) -> 3700 | Q79: 0 | R79: =M79+(M79*Q79) -> 3700 | S79: =IFERROR(((R79-P79)/R79),0) -> 0 | T79: =IF(C79="Mediana Complejidad",M79,0) -> 0 | U79: 0 | V79: =(T79)+(T79*U79) -> 0 | W79: =IFERROR(((V79-T79)/V79),0) -> 0 | X79: =IF(C79="Baja Complejidad",M79,0) -> 0 | Y79: 0 | Z79: =(X79)+(X79*Y79) -> 0 | AA79: =IFERROR(((Z79-X79)/Z79),0) -> 0 | AB79: 0.1
A80: 2026 | B80: Agosto | C80: Alta Complejidad | D80: Curación de ALTA COMPLEJIDAD | E80: S60 | G80: INSUMO | H80: INSUMO | I80: Solucion Salina 0.9% Bolsa 500 ml | J80: 2 | K80: UND | L80: 2643 | M80: 5286 | O80: =R80 -> 5286 | P80: =IF(C80="Alta Complejidad",M80,0) -> 5286 | Q80: 0 | R80: =M80+(M80*Q80) -> 5286 | S80: =IFERROR(((R80-P80)/R80),0) -> 0 | T80: =IF(C80="Mediana Complejidad",M80,0) -> 0 | U80: 0 | V80: =(T80)+(T80*U80) -> 0 | W80: =IFERROR(((V80-T80)/V80),0) -> 0 | X80: =IF(C80="Baja Complejidad",M80,0) -> 0 | Y80: 0 | Z80: =(X80)+(X80*Y80) -> 0 | AA80: =IFERROR(((Z80-X80)/Z80),0) -> 0 | AB80: 0.1
A81: 2026 | B81: Agosto | C81: Alta Complejidad | D81: Curación de ALTA COMPLEJIDAD | E81: T502 | G81: INSUMO | H81: INSUMO | I81: Tapabocas Estandar 1405 | J81: 5 | K81: UND | L81: 135.66 | M81: 678.3 | O81: =R81 -> 678.3 | P81: =IF(C81="Alta Complejidad",M81,0) -> 678.3 | Q81: 0 | R81: =M81+(M81*Q81) -> 678.3 | S81: =IFERROR(((R81-P81)/R81),0) -> 0 | T81: =IF(C81="Mediana Complejidad",M81,0) -> 0 | U81: 0 | V81: =(T81)+(T81*U81) -> 0 | W81: =IFERROR(((V81-T81)/V81),0) -> 0 | X81: =IF(C81="Baja Complejidad",M81,0) -> 0 | Y81: 0 | Z81: =(X81)+(X81*Y81) -> 0 | AA81: =IFERROR(((Z81-X81)/Z81),0) -> 0 | AB81: 0.1
A82: 2026 | B82: Agosto | C82: Alta Complejidad | D82: Curación de ALTA COMPLEJIDAD | E82: B10 | G82: INSUMO | H82: INSUMO | I82: Bata Desechable con Manga No Esteril | J82: 2 | K82: UND | L82: 3808 | M82: 7616 | O82: =R82 -> 7616 | P82: =IF(C82="Alta Complejidad",M82,0) -> 7616 | Q82: 0 | R82: =M82+(M82*Q82) -> 7616 | S82: =IFERROR(((R82-P82)/R82),0) -> 0 | T82: =IF(C82="Mediana Complejidad",M82,0) -> 0 | U82: 0 | V82: =(T82)+(T82*U82) -> 0 | W82: =IFERROR(((V82-T82)/V82),0) -> 0 | X82: =IF(C82="Baja Complejidad",M82,0) -> 0 | Y82: 0 | Z82: =(X82)+(X82*Y82) -> 0 | AA82: =IFERROR(((Z82-X82)/Z82),0) -> 0 | AB82: 0.1
A83: 2026 | B83: Agosto | C83: Alta Complejidad | D83: Curación de ALTA COMPLEJIDAD | E83: G07 | G83: INSUMO | H83: INSUMO | I83: Gorro Desechable Estandar Blanco | J83: 2 | K83: UND | L83: 111.86 | M83: 223.72 | O83: =R83 -> 223.72 | P83: =IF(C83="Alta Complejidad",M83,0) -> 223.72 | Q83: 0 | R83: =M83+(M83*Q83) -> 223.72 | S83: =IFERROR(((R83-P83)/R83),0) -> 0 | T83: =IF(C83="Mediana Complejidad",M83,0) -> 0 | U83: 0 | V83: =(T83)+(T83*U83) -> 0 | W83: =IFERROR(((V83-T83)/V83),0) -> 0 | X83: =IF(C83="Baja Complejidad",M83,0) -> 0 | Y83: 0 | Z83: =(X83)+(X83*Y83) -> 0 | AA83: =IFERROR(((Z83-X83)/Z83),0) -> 0 | AB83: 0.1
A84: 2026 | B84: Agosto | C84: Alta Complejidad | D84: Curación de ALTA COMPLEJIDAD | E84: 360100 | G84: INSUMO | H84: INSUMO | I84: Granudacyn Solución 250 ml Spray | J84: 10 | K84: UND | L84: 80300 | M84: 3212 | O84: =R84 -> 3212 | P84: =IF(C84="Alta Complejidad",M84,0) -> 3212 | Q84: 0 | R84: =M84+(M84*Q84) -> 3212 | S84: =IFERROR(((R84-P84)/R84),0) -> 0 | T84: =IF(C84="Mediana Complejidad",M84,0) -> 0 | U84: 0 | V84: =(T84)+(T84*U84) -> 0 | W84: =IFERROR(((V84-T84)/V84),0) -> 0 | X84: =IF(C84="Baja Complejidad",M84,0) -> 0 | Y84: 0 | Z84: =(X84)+(X84*Y84) -> 0 | AA84: =IFERROR(((Z84-X84)/Z84),0) -> 0 | AB84: 0.1
A85: 2026 | B85: Agosto | C85: Alta Complejidad | D85: Curación de ALTA COMPLEJIDAD | E85: T180 | G85: INSUMO | H85: INSUMO | I85: Toalla de Manos Pre-cortada Natural R7 | J85: 5 | K85: UND | L85: 17888.08 | M85: 89440.4 | O85: =R85 -> 89440.4 | P85: =IF(C85="Alta Complejidad",M85,0) -> 89440.4 | Q85: 0 | R85: =M85+(M85*Q85) -> 89440.4 | S85: =IFERROR(((R85-P85)/R85),0) -> 0 | T85: =IF(C85="Mediana Complejidad",M85,0) -> 0 | U85: 0 | V85: =(T85)+(T85*U85) -> 0 | W85: =IFERROR(((V85-T85)/V85),0) -> 0 | X85: =IF(C85="Baja Complejidad",M85,0) -> 0 | Y85: 0 | Z85: =(X85)+(X85*Y85) -> 0 | AA85: =IFERROR(((Z85-X85)/Z85),0) -> 0 | AB85: 0.1
A86: 2026 | B86: Agosto | C86: Alta Complejidad | D86: Curación de ALTA COMPLEJIDAD | E86: H15 | G86: INSUMO | H86: INSUMO | I86: Hoja para bisturi 15 | J86: 2 | K86: UND | L86: 337.38379 | M86: 674.76758 | O86: =R86 -> 674.76758 | P86: =IF(C86="Alta Complejidad",M86,0) -> 674.76758 | Q86: 0 | R86: =M86+(M86*Q86) -> 674.76758 | S86: =IFERROR(((R86-P86)/R86),0) -> 0 | T86: =IF(C86="Mediana Complejidad",M86,0) -> 0 | U86: 0 | V86: =(T86)+(T86*U86) -> 0 | W86: =IFERROR(((V86-T86)/V86),0) -> 0 | X86: =IF(C86="Baja Complejidad",M86,0) -> 0 | Y86: 0 | Z86: =(X86)+(X86*Y86) -> 0 | AA86: =IFERROR(((Z86-X86)/Z86),0) -> 0 | AB86: 0.1
A87: 2026 | B87: Agosto | C87: Alta Complejidad | D87: Curación de ALTA COMPLEJIDAD | E87: 2438 | G87: INSUMO | H87: INSUMO | I87: Tubifast 10m Azul | J87: 2 | K87: UND | L87: 67900 | M87: 13580 | O87: =R87 -> 13580 | P87: =IF(C87="Alta Complejidad",M87,0) -> 13580 | Q87: 0 | R87: =M87+(M87*Q87) -> 13580 | S87: =IFERROR(((R87-P87)/R87),0) -> 0 | T87: =IF(C87="Mediana Complejidad",M87,0) -> 0 | U87: 0 | V87: =(T87)+(T87*U87) -> 0 | W87: =IFERROR(((V87-T87)/V87),0) -> 0 | X87: =IF(C87="Baja Complejidad",M87,0) -> 0 | Y87: 0 | Z87: =(X87)+(X87*Y87) -> 0 | AA87: =IFERROR(((Z87-X87)/Z87),0) -> 0 | AB87: 0.1
A88: 2026 | B88: Agosto | C88: Alta Complejidad | D88: Curación de ALTA COMPLEJIDAD | E88: 2434 | G88: INSUMO | H88: INSUMO | I88: Tubifast 10m Rojo | J88: 2 | K88: UND | L88: 50300 | M88: 10060 | O88: =R88 -> 10060 | P88: =IF(C88="Alta Complejidad",M88,0) -> 10060 | Q88: 0 | R88: =M88+(M88*Q88) -> 10060 | S88: =IFERROR(((R88-P88)/R88),0) -> 0 | T88: =IF(C88="Mediana Complejidad",M88,0) -> 0 | U88: 0 | V88: =(T88)+(T88*U88) -> 0 | W88: =IFERROR(((V88-T88)/V88),0) -> 0 | X88: =IF(C88="Baja Complejidad",M88,0) -> 0 | Y88: 0 | Z88: =(X88)+(X88*Y88) -> 0 | AA88: =IFERROR(((Z88-X88)/Z88),0) -> 0 | AB88: 0.1
A89: 2026 | B89: Agosto | C89: Alta Complejidad | D89: Curación de ALTA COMPLEJIDAD | E89: 3505 | G89: INSUMO | H89: INSUMO | I89: Setopress 10 cm x 3.5 m Relaxed x 12 | J89: 2 | K89: UND | L89: 43500 | M89: 7250 | O89: =R89 -> 7250 | P89: =IF(C89="Alta Complejidad",M89,0) -> 7250 | Q89: 0 | R89: =M89+(M89*Q89) -> 7250 | S89: =IFERROR(((R89-P89)/R89),0) -> 0 | T89: =IF(C89="Mediana Complejidad",M89,0) -> 0 | U89: 0 | V89: =(T89)+(T89*U89) -> 0 | W89: =IFERROR(((V89-T89)/V89),0) -> 0 | X89: =IF(C89="Baja Complejidad",M89,0) -> 0 | Y89: 0 | Z89: =(X89)+(X89*Y89) -> 0 | AA89: =IFERROR(((Z89-X89)/Z89),0) -> 0 | AB89: 0.1
A90: 2026 | B90: Agosto | C90: Alta Complejidad | D90: Curación de ALTA COMPLEJIDAD | F90: 1800 | G90: MANO_OBRA | H90: MANO_OBRA | I90: Enfermera | J90: 60 | K90: MINUTOS | L90: 20894.4 | M90: =+L90*J90 -> 1253664 | O90: =R90 -> 1253664 | P90: =IF(C90="Alta Complejidad",M90,0) -> 1253664 | Q90: 0 | R90: =M90+(M90*Q90) -> 1253664 | S90: =IFERROR(((R90-P90)/R90),0) -> 0 | T90: =IF(C90="Mediana Complejidad",M90,0) -> 0 | U90: 0 | V90: =(T90)+(T90*U90) -> 0 | W90: =IFERROR(((V90-T90)/V90),0) -> 0 | X90: =IF(C90="Baja Complejidad",M90,0) -> 0 | Y90: 0 | Z90: =(X90)+(X90*Y90) -> 0 | AA90: =IFERROR(((Z90-X90)/Z90),0) -> 0 | AB90: 0.1
A91: 2026 | B91: Agosto | C91: Alta Complejidad | D91: Curación de ALTA COMPLEJIDAD | F91: 900 | G91: MANO_OBRA | H91: MANO_OBRA | I91: Auxiliar enfermeria | J91: 60 | K91: MINUTOS | L91: 6048.3 | M91: =+L91*J91 -> 362898 | O91: =R91 -> 362898 | P91: =IF(C91="Alta Complejidad",M91,0) -> 362898 | Q91: 0 | R91: =M91+(M91*Q91) -> 362898 | S91: =IFERROR(((R91-P91)/R91),0) -> 0 | T91: =IF(C91="Mediana Complejidad",M91,0) -> 0 | U91: 0 | V91: =(T91)+(T91*U91) -> 0 | W91: =IFERROR(((V91-T91)/V91),0) -> 0 | X91: =IF(C91="Baja Complejidad",M91,0) -> 0 | Y91: 0 | Z91: =(X91)+(X91*Y91) -> 0 | AA91: =IFERROR(((Z91-X91)/Z91),0) -> 0 | AB91: 0.1
A92: 2026 | B92: Agosto | C92: Alta Complejidad | D92: Curación de ALTA COMPLEJIDAD | F92: 600 | G92: MANO_OBRA | H92: MANO_OBRA | I92: Cirujano vascular | J92: 60 | K92: MINUTOS | L92: 35000 | M92: =+L92*J92 -> 2100000 | O92: =R92 -> 2100000 | P92: =IF(C92="Alta Complejidad",M92,0) -> 2100000 | Q92: 0 | R92: =M92+(M92*Q92) -> 2100000 | S92: =IFERROR(((R92-P92)/R92),0) -> 0 | T92: =IF(C92="Mediana Complejidad",M92,0) -> 0 | U92: 0 | V92: =(T92)+(T92*U92) -> 0 | W92: =IFERROR(((V92-T92)/V92),0) -> 0 | X92: =IF(C92="Baja Complejidad",M92,0) -> 0 | Y92: 0 | Z92: =(X92)+(X92*Y92) -> 0 | AA92: =IFERROR(((Z92-X92)/Z92),0) -> 0 | AB92: 0.1
A93: 2026 | B93: Agosto | C93: Alta Complejidad | D93: Curación de ALTA COMPLEJIDAD | F93: 600 | G93: MANO_OBRA | H93: MANO_OBRA | I93: Nutricionista | J93: 60 | K93: MINUTOS | L93: 25000 | M93: =+L93*J93 -> 1500000 | O93: =R93 -> 1500000 | P93: =IF(C93="Alta Complejidad",M93,0) -> 1500000 | Q93: 0 | R93: =M93+(M93*Q93) -> 1500000 | S93: =IFERROR(((R93-P93)/R93),0) -> 0 | T93: =IF(C93="Mediana Complejidad",M93,0) -> 0 | U93: 0 | V93: =(T93)+(T93*U93) -> 0 | W93: =IFERROR(((V93-T93)/V93),0) -> 0 | X93: =IF(C93="Baja Complejidad",M93,0) -> 0 | Y93: 0 | Z93: =(X93)+(X93*Y93) -> 0 | AA93: =IFERROR(((Z93-X93)/Z93),0) -> 0 | AB93: 0.1
A94: 2026 | B94: Agosto | C94: Alta Complejidad | D94: Curación de ALTA COMPLEJIDAD | F94: 600 | G94: MANO_OBRA | H94: MANO_OBRA | I94: Terapeuta fisico | J94: 60 | K94: MINUTOS | L94: 20000 | M94: =+L94*J94 -> 1200000 | O94: =R94 -> 1200000 | P94: =IF(C94="Alta Complejidad",M94,0) -> 1200000 | Q94: 0 | R94: =M94+(M94*Q94) -> 1200000 | S94: =IFERROR(((R94-P94)/R94),0) -> 0 | T94: =IF(C94="Mediana Complejidad",M94,0) -> 0 | U94: 0 | V94: =(T94)+(T94*U94) -> 0 | W94: =IFERROR(((V94-T94)/V94),0) -> 0 | X94: =IF(C94="Baja Complejidad",M94,0) -> 0 | Y94: 0 | Z94: =(X94)+(X94*Y94) -> 0 | AA94: =IFERROR(((Z94-X94)/Z94),0) -> 0 | AB94: 0.1
A95: 2026 | B95: Septiembre | C95: Alta Complejidad | D95: Curación de ALTA COMPLEJIDAD | E95: G20 | G95: INSUMO | H95: INSUMO | I95: Guante examen talla M | J95: 4 | K95: UND | L95: 266 | M95: 1064 | O95: =R95 -> 1064 | P95: =IF(C95="Alta Complejidad",M95,0) -> 1064 | Q95: 0 | R95: =M95+(M95*Q95) -> 1064 | S95: =IFERROR(((R95-P95)/R95),0) -> 0 | T95: =IF(C95="Mediana Complejidad",M95,0) -> 0 | U95: 0 | V95: =(T95)+(T95*U95) -> 0 | W95: =IFERROR(((V95-T95)/V95),0) -> 0 | X95: =IF(C95="Baja Complejidad",M95,0) -> 0 | Y95: 0 | Z95: =(X95)+(X95*Y95) -> 0 | AA95: =IFERROR(((Z95-X95)/Z95),0) -> 0 | AB95: 0.1
A96: 2026 | B96: Septiembre | C96: Alta Complejidad | D96: Curación de ALTA COMPLEJIDAD | E96: G68 | G96: INSUMO | H96: INSUMO | I96: Guante quirurgico esteril 7.0 | J96: 2 | K96: UND | L96: 1086.232 | M96: 2172.464 | O96: =R96 -> 2172.464 | P96: =IF(C96="Alta Complejidad",M96,0) -> 2172.464 | Q96: 0 | R96: =M96+(M96*Q96) -> 2172.464 | S96: =IFERROR(((R96-P96)/R96),0) -> 0 | T96: =IF(C96="Mediana Complejidad",M96,0) -> 0 | U96: 0 | V96: =(T96)+(T96*U96) -> 0 | W96: =IFERROR(((V96-T96)/V96),0) -> 0 | X96: =IF(C96="Baja Complejidad",M96,0) -> 0 | Y96: 0 | Z96: =(X96)+(X96*Y96) -> 0 | AA96: =IFERROR(((Z96-X96)/Z96),0) -> 0 | AB96: 0.1
A97: 2026 | B97: Septiembre | C97: Alta Complejidad | D97: Curación de ALTA COMPLEJIDAD | E97: G75 | G97: INSUMO | H97: INSUMO | I97: Gasa esteril 7.5 X 7.5 sobre x 5 unid | J97: 10 | K97: UND | L97: 370 | M97: 3700 | O97: =R97 -> 3700 | P97: =IF(C97="Alta Complejidad",M97,0) -> 3700 | Q97: 0 | R97: =M97+(M97*Q97) -> 3700 | S97: =IFERROR(((R97-P97)/R97),0) -> 0 | T97: =IF(C97="Mediana Complejidad",M97,0) -> 0 | U97: 0 | V97: =(T97)+(T97*U97) -> 0 | W97: =IFERROR(((V97-T97)/V97),0) -> 0 | X97: =IF(C97="Baja Complejidad",M97,0) -> 0 | Y97: 0 | Z97: =(X97)+(X97*Y97) -> 0 | AA97: =IFERROR(((Z97-X97)/Z97),0) -> 0 | AB97: 0.1
A98: 2026 | B98: Septiembre | C98: Alta Complejidad | D98: Curación de ALTA COMPLEJIDAD | E98: S60 | G98: INSUMO | H98: INSUMO | I98: Solucion Salina 0.9% Bolsa 500 ml | J98: 2 | K98: UND | L98: 2643 | M98: 5286 | O98: =R98 -> 5286 | P98: =IF(C98="Alta Complejidad",M98,0) -> 5286 | Q98: 0 | R98: =M98+(M98*Q98) -> 5286 | S98: =IFERROR(((R98-P98)/R98),0) -> 0 | T98: =IF(C98="Mediana Complejidad",M98,0) -> 0 | U98: 0 | V98: =(T98)+(T98*U98) -> 0 | W98: =IFERROR(((V98-T98)/V98),0) -> 0 | X98: =IF(C98="Baja Complejidad",M98,0) -> 0 | Y98: 0 | Z98: =(X98)+(X98*Y98) -> 0 | AA98: =IFERROR(((Z98-X98)/Z98),0) -> 0 | AB98: 0.1
A99: 2026 | B99: Septiembre | C99: Alta Complejidad | D99: Curación de ALTA COMPLEJIDAD | E99: T502 | G99: INSUMO | H99: INSUMO | I99: Tapabocas Estandar 1405 | J99: 5 | K99: UND | L99: 135.66 | M99: 678.3 | O99: =R99 -> 678.3 | P99: =IF(C99="Alta Complejidad",M99,0) -> 678.3 | Q99: 0 | R99: =M99+(M99*Q99) -> 678.3 | S99: =IFERROR(((R99-P99)/R99),0) -> 0 | T99: =IF(C99="Mediana Complejidad",M99,0) -> 0 | U99: 0 | V99: =(T99)+(T99*U99) -> 0 | W99: =IFERROR(((V99-T99)/V99),0) -> 0 | X99: =IF(C99="Baja Complejidad",M99,0) -> 0 | Y99: 0 | Z99: =(X99)+(X99*Y99) -> 0 | AA99: =IFERROR(((Z99-X99)/Z99),0) -> 0 | AB99: 0.1
A100: 2026 | B100: Septiembre | C100: Alta Complejidad | D100: Curación de ALTA COMPLEJIDAD | E100: B10 | G100: INSUMO | H100: INSUMO | I100: Bata Desechable con Manga No Esteril | J100: 2 | K100: UND | L100: 3808 | M100: 7616 | O100: =R100 -> 7616 | P100: =IF(C100="Alta Complejidad",M100,0) -> 7616 | Q100: 0 | R100: =M100+(M100*Q100) -> 7616 | S100: =IFERROR(((R100-P100)/R100),0) -> 0 | T100: =IF(C100="Mediana Complejidad",M100,0) -> 0 | U100: 0 | V100: =(T100)+(T100*U100) -> 0 | W100: =IFERROR(((V100-T100)/V100),0) -> 0 | X100: =IF(C100="Baja Complejidad",M100,0) -> 0 | Y100: 0 | Z100: =(X100)+(X100*Y100) -> 0 | AA100: =IFERROR(((Z100-X100)/Z100),0) -> 0 | AB100: 0.1
A101: 2026 | B101: Septiembre | C101: Alta Complejidad | D101: Curación de ALTA COMPLEJIDAD | E101: G07 | G101: INSUMO | H101: INSUMO | I101: Gorro Desechable Estandar Blanco | J101: 2 | K101: UND | L101: 111.86 | M101: 223.72 | O101: =R101 -> 223.72 | P101: =IF(C101="Alta Complejidad",M101,0) -> 223.72 | Q101: 0 | R101: =M101+(M101*Q101) -> 223.72 | S101: =IFERROR(((R101-P101)/R101),0) -> 0 | T101: =IF(C101="Mediana Complejidad",M101,0) -> 0 | U101: 0 | V101: =(T101)+(T101*U101) -> 0 | W101: =IFERROR(((V101-T101)/V101),0) -> 0 | X101: =IF(C101="Baja Complejidad",M101,0) -> 0 | Y101: 0 | Z101: =(X101)+(X101*Y101) -> 0 | AA101: =IFERROR(((Z101-X101)/Z101),0) -> 0 | AB101: 0.1
A102: 2026 | B102: Septiembre | C102: Alta Complejidad | D102: Curación de ALTA COMPLEJIDAD | E102: 360100 | G102: INSUMO | H102: INSUMO | I102: Granudacyn Solución 250 ml Spray | J102: 10 | K102: UND | L102: 80300 | M102: 3212 | O102: =R102 -> 3212 | P102: =IF(C102="Alta Complejidad",M102,0) -> 3212 | Q102: 0 | R102: =M102+(M102*Q102) -> 3212 | S102: =IFERROR(((R102-P102)/R102),0) -> 0 | T102: =IF(C102="Mediana Complejidad",M102,0) -> 0 | U102: 0 | V102: =(T102)+(T102*U102) -> 0 | W102: =IFERROR(((V102-T102)/V102),0) -> 0 | X102: =IF(C102="Baja Complejidad",M102,0) -> 0 | Y102: 0 | Z102: =(X102)+(X102*Y102) -> 0 | AA102: =IFERROR(((Z102-X102)/Z102),0) -> 0 | AB102: 0.1
A103: 2026 | B103: Septiembre | C103: Alta Complejidad | D103: Curación de ALTA COMPLEJIDAD | E103: T180 | G103: INSUMO | H103: INSUMO | I103: Toalla de Manos Pre-cortada Natural R7 | J103: 5 | K103: UND | L103: 17888.08 | M103: 89440.4 | O103: =R103 -> 89440.4 | P103: =IF(C103="Alta Complejidad",M103,0) -> 89440.4 | Q103: 0 | R103: =M103+(M103*Q103) -> 89440.4 | S103: =IFERROR(((R103-P103)/R103),0) -> 0 | T103: =IF(C103="Mediana Complejidad",M103,0) -> 0 | U103: 0 | V103: =(T103)+(T103*U103) -> 0 | W103: =IFERROR(((V103-T103)/V103),0) -> 0 | X103: =IF(C103="Baja Complejidad",M103,0) -> 0 | Y103: 0 | Z103: =(X103)+(X103*Y103) -> 0 | AA103: =IFERROR(((Z103-X103)/Z103),0) -> 0 | AB103: 0.1
A104: 2026 | B104: Septiembre | C104: Alta Complejidad | D104: Curación de ALTA COMPLEJIDAD | E104: H15 | G104: INSUMO | H104: INSUMO | I104: Hoja para bisturi 15 | J104: 2 | K104: UND | L104: 337.38379 | M104: 674.76758 | O104: =R104 -> 674.76758 | P104: =IF(C104="Alta Complejidad",M104,0) -> 674.76758 | Q104: 0 | R104: =M104+(M104*Q104) -> 674.76758 | S104: =IFERROR(((R104-P104)/R104),0) -> 0 | T104: =IF(C104="Mediana Complejidad",M104,0) -> 0 | U104: 0 | V104: =(T104)+(T104*U104) -> 0 | W104: =IFERROR(((V104-T104)/V104),0) -> 0 | X104: =IF(C104="Baja Complejidad",M104,0) -> 0 | Y104: 0 | Z104: =(X104)+(X104*Y104) -> 0 | AA104: =IFERROR(((Z104-X104)/Z104),0) -> 0 | AB104: 0.1
A105: 2026 | B105: Septiembre | C105: Alta Complejidad | D105: Curación de ALTA COMPLEJIDAD | E105: 2438 | G105: INSUMO | H105: INSUMO | I105: Tubifast 10m Azul | J105: 2 | K105: UND | L105: 67900 | M105: 13580 | O105: =R105 -> 13580 | P105: =IF(C105="Alta Complejidad",M105,0) -> 13580 | Q105: 0 | R105: =M105+(M105*Q105) -> 13580 | S105: =IFERROR(((R105-P105)/R105),0) -> 0 | T105: =IF(C105="Mediana Complejidad",M105,0) -> 0 | U105: 0 | V105: =(T105)+(T105*U105) -> 0 | W105: =IFERROR(((V105-T105)/V105),0) -> 0 | X105: =IF(C105="Baja Complejidad",M105,0) -> 0 | Y105: 0 | Z105: =(X105)+(X105*Y105) -> 0 | AA105: =IFERROR(((Z105-X105)/Z105),0) -> 0 | AB105: 0.1
A106: 2026 | B106: Septiembre | C106: Alta Complejidad | D106: Curación de ALTA COMPLEJIDAD | E106: 2434 | G106: INSUMO | H106: INSUMO | I106: Tubifast 10m Rojo | J106: 2 | K106: UND | L106: 50300 | M106: 10060 | O106: =R106 -> 10060 | P106: =IF(C106="Alta Complejidad",M106,0) -> 10060 | Q106: 0 | R106: =M106+(M106*Q106) -> 10060 | S106: =IFERROR(((R106-P106)/R106),0) -> 0 | T106: =IF(C106="Mediana Complejidad",M106,0) -> 0 | U106: 0 | V106: =(T106)+(T106*U106) -> 0 | W106: =IFERROR(((V106-T106)/V106),0) -> 0 | X106: =IF(C106="Baja Complejidad",M106,0) -> 0 | Y106: 0 | Z106: =(X106)+(X106*Y106) -> 0 | AA106: =IFERROR(((Z106-X106)/Z106),0) -> 0 | AB106: 0.1
A107: 2026 | B107: Septiembre | C107: Alta Complejidad | D107: Curación de ALTA COMPLEJIDAD | E107: 3505 | G107: INSUMO | H107: INSUMO | I107: Setopress 10 cm x 3.5 m Relaxed x 12 | J107: 2 | K107: UND | L107: 43500 | M107: 7250 | O107: =R107 -> 7250 | P107: =IF(C107="Alta Complejidad",M107,0) -> 7250 | Q107: 0 | R107: =M107+(M107*Q107) -> 7250 | S107: =IFERROR(((R107-P107)/R107),0) -> 0 | T107: =IF(C107="Mediana Complejidad",M107,0) -> 0 | U107: 0 | V107: =(T107)+(T107*U107) -> 0 | W107: =IFERROR(((V107-T107)/V107),0) -> 0 | X107: =IF(C107="Baja Complejidad",M107,0) -> 0 | Y107: 0 | Z107: =(X107)+(X107*Y107) -> 0 | AA107: =IFERROR(((Z107-X107)/Z107),0) -> 0 | AB107: 0.1
A108: 2026 | B108: Septiembre | C108: Alta Complejidad | D108: Curación de ALTA COMPLEJIDAD | F108: 1800 | G108: MANO_OBRA | H108: MANO_OBRA | I108: Enfermera | J108: 60 | K108: MINUTOS | L108: 20894.4 | M108: =+L108*J108 -> 1253664 | O108: =R108 -> 1253664 | P108: =IF(C108="Alta Complejidad",M108,0) -> 1253664 | Q108: 0 | R108: =M108+(M108*Q108) -> 1253664 | S108: =IFERROR(((R108-P108)/R108),0) -> 0 | T108: =IF(C108="Mediana Complejidad",M108,0) -> 0 | U108: 0 | V108: =(T108)+(T108*U108) -> 0 | W108: =IFERROR(((V108-T108)/V108),0) -> 0 | X108: =IF(C108="Baja Complejidad",M108,0) -> 0 | Y108: 0 | Z108: =(X108)+(X108*Y108) -> 0 | AA108: =IFERROR(((Z108-X108)/Z108),0) -> 0 | AB108: 0.1
...

Sheet formulas
A1: FORMULAS APLICADASD
A2: PUNTO EQUILIBRIO
A8: MARGEN
